Workbook

Sheet M&A & Financial metrics
D1: Profitability Ratio | H1: Liquidity Ratio | K1: Solvency Ratio
A2: Year t | B2: Number of Acquisitions t | C2: Amount spent for acquistion ($) | D2: ROA t (%) | E2: ROE t (%) | F2: Net profit margin (%) | G2: ESP basics (US $) | H2: Current Ratio (%) | I2: Quick Ratio (%) | J2: Cash ratio (%) | K2: Total Debt/Total Assets (%) | L2: Total Debt/ Total Equity (%) | M2: Net debt/E (%) | N2: Revenue ($) | O2: Market capitalization ($)
A3: 2024 | B3: =SUMPRODUCT(('M&A Deals'!H:H = "Buyer") * (RIGHT('M&A Deals'!B:B, 2) = RIGHT(A3, 2))) -> 4 | C3: 2931000000 | D3: {=TRANSPOSE('Ratios Factset'!B18:V18)} -> 23,48 | E3: {=TRANSPOSE('Ratios Factset'!B19:V19)} -> 32,91 | F3: {=TRANSPOSE('Ratios Factset'!B15:V15)} -> 28,62 | G3: {=TRANSPOSE('Ratios Factset'!B40:V40)} -> 8,13 | H3: {=TRANSPOSE('Ratios Factset'!B86:V86)} -> 1,84 | I3: {=TRANSPOSE('Ratios Factset'!B87:V87)} -> 1,84 | J3: {=TRANSPOSE('Ratios Factset'!B88:V88)} -> 1,07 | K3: {=TRANSPOSE('Ratios Factset'!B112:V112)} -> 6,25 | L3: {=TRANSPOSE('Ratios Factset'!B114:V114)} -> 8,66 | M3: {=TRANSPOSE('Ratios Factset'!B113:V113)} -> -20,77 | N3: 349810000000 | O3: 2317220000000
A4: 2023 | B4: =SUMPRODUCT(('M&A Deals'!H:H = "Buyer") * (RIGHT('M&A Deals'!B:B, 2) = RIGHT(A4, 2))) -> 2 | C4: 495000000 | D4: 19,23 | E4: 27,36 | F4: 24,03 | G4: 5,84 | H4: 2,10 | I4: 2,10 | J4: 1,36 | K4: 7,42 | L4: 10,54 | M4: -28,60 | N4: 307160000000 | O4: 1748360000000
A5: 2022 | B5: =SUMPRODUCT(('M&A Deals'!H:H = "Buyer") * (RIGHT('M&A Deals'!B:B, 2) = RIGHT(A5, 2))) -> 16 | C5: 6969000000 | D5: 16,55 | E5: 23,62 | F5: 21,35 | G5: 4,59 | H5: 2,38 | I5: 2,34 | J5: 1,64 | K5: 8,21 | L5: 11,70 | M5: -32,71 | N5: 280880000000 | O5: 1141960000000
A6: 2021 | B6: =SUMPRODUCT(('M&A Deals'!H:H = "Buyer") * (RIGHT('M&A Deals'!B:B, 2) = RIGHT(A6, 2))) -> 15 | C6: 2618000000 | D6: 22,40 | E6: 32,07 | F6: 29,53 | G6: 5,69 | H6: 2,93 | I6: 2,91 | J6: 2,17 | K6: 7,94 | L6: 11,33 | M6: -44,17 | N6: 257490000000 | O6: 1922950000000
A7: 2020 | B7: =SUMPRODUCT(('M&A Deals'!H:H = "Buyer") * (RIGHT('M&A Deals'!B:B, 2) = RIGHT(A7, 2))) -> 10 | C7: 738000000 | D7: 13,52 | E7: 19,00 | F7: 22,08 | G7: 2,96 | H7: 3,07 | I7: 3,05 | J7: 2,41 | K7: 8,72 | L7: 12,52 | M7: -48,90 | N7: 182350000000 | O7: 1185830000000
A8: 2019 | B8: =SUMPRODUCT(('M&A Deals'!H:H = "Buyer") * (RIGHT('M&A Deals'!B:B, 2) = RIGHT(A8, 2))) -> 9 | C8: 2515000000 | D8: 13,50 | E8: 18,12 | F8: 21,28 | G8: 2,48 | H8: 3,37 | I8: 3,35 | J8: 2,65 | K8: 5,79 | L8: 7,93 | M8: -51,48 | N8: 161400000000 | O8: 923770000000
A9: 2018 | B9: =SUMPRODUCT(('M&A Deals'!H:H = "Buyer") * (RIGHT('M&A Deals'!B:B, 2) = RIGHT(A9, 2))) -> 15 | C9: 1491000000 | D9: 14,29 | E9: 18,62 | F9: 22,44 | G9: 2,21 | H9: 3,92 | I9: 3,89 | J9: 3,15 | K9: 1,72 | L9: 2,26 | M9: -59,18 | N9: 136960000000 | O9: 726730000000
A10: 2017 | B10: =SUMPRODUCT(('M&A Deals'!H:H = "Buyer") * (RIGHT('M&A Deals'!B:B, 2) = RIGHT(A10, 2))) -> 15 | C10: 287000000 | D10: 6,94 | E10: 8,69 | F10: 11,40 | G10: 0,91 | H10: 5,14 | I10: 5,11 | J10: 4,21 | K10: 2,01 | L10: 2,60 | M10: -64,20 | N10: 111020000000 | O10: 731900000000
A11: 2016 | B11: =SUMPRODUCT(('M&A Deals'!H:H = "Buyer") * (RIGHT('M&A Deals'!B:B, 2) = RIGHT(A11, 2))) -> 21 | C11: 986000000 | D11: 12,37 | E11: 15,02 | F11: 21,71 | G11: 1,42 | H11: 6,29 | I11: 6,27 | J11: 5,15 | K11: 2,35 | L11: 2,83 | M11: -59,26 | N11: 89730000000 | O11: 546190000000
A12: 2015 | B12: =SUMPRODUCT(('M&A Deals'!H:H = "Buyer") * (RIGHT('M&A Deals'!B:B, 2) = RIGHT(A12, 2))) -> 38 | C12: 236000000 | D12: 11,44 | E12: 14,12 | F12: 21,51 | G12: 1,16 | H12: 4,67 | I12: 4,64 | J12: 3,78 | K12: 3,54 | L12: 4,34 | M12: -56,38 | N12: 73590000000 | O12: 535060000000
A13: 2014 | B13: =SUMPRODUCT(('M&A Deals'!H:H = "Buyer") * (RIGHT('M&A Deals'!B:B, 2) = RIGHT(A13, 2))) -> 44 | C13: 4888000000 | D13: 11,34 | E13: 14,25 | F13: 20,69 | G13: 0,99 | H13: 4,69 | I13: 4,69 | J13: 3,84 | K13: 4,05 | L13: 5,04 | M13: -56,96 | N13: 65830000000 | O13: 359980000000
A14: 2013 | B14: =SUMPRODUCT(('M&A Deals'!H:H = "Buyer") * (RIGHT('M&A Deals'!B:B, 2) = RIGHT(A14, 2))) -> 21 | C14: 1448000000 | D14: 11,93 | E14: 15,36 | F14: 20,45 | G14: 0,91 | H14: 4,58 | I14: 4,55 | J14: 3,69 | K14: 4,73 | L14: 6,01 | M14: -61,24 | N14: 59730000000 | O14: 374790000000
A15: 2012 | B15: =SUMPRODUCT(('M&A Deals'!H:H = "Buyer") * (RIGHT('M&A Deals'!B:B, 2) = RIGHT(A15, 2))) -> 16 | C15: 10568000000 | D15: 12,97 | E15: 16,61 | F15: 21,59 | G15: 0,82 | H15: 4,22 | I15: 4,18 | J15: 3,35 | K15: 5,90 | L15: 7,72 | M15: -59,33 | N15: 49960000000 | O15: 231570000000
... A23: 2004 | B23: =SUMPRODUCT(('M&A Deals'!H:H = "Buyer") * (RIGHT('M&A Deals'!B:B, 2) = RIGHT(A23, 2))) -> 3 | C23: 58863000 | D23: 19,08 | E23: 22,57 | F23: 12,51 | G23: 0,05 | H23: 7,91 | I23: 7,91 | J23: 6,30 | K23: 0,06 | L23: 0,06 | M23: -73,11 | N23: 3190000000 | O23: 52770000000

Sheet Market Cap
A1: Market Cap History Alphabet Inc. (GOOGL)
A2: Date | B2: Market Cap | C2: % Change
A3: 45764 | B3: 1,842.64B | C3: -20.48%
A4: Dec 31, 2024 | B4: 2,317.22B | C4: 32.54%
A5: Dec 29, 2023 | B5: 1,748.36B | C5: 53.10%
A6: Dec 30, 2022 | B6: 1,141.96B | C6: -40.61%
A7: Dec 31, 2021 | B7: 1,922.95B | C7: 62.20%
A8: Dec 31, 2020 | B8: 1,185.53B | C8: 28.34%
A9: Dec 31, 2019 | B9: 923.77B | C9: 27.11%
A10: Dec 31, 2018 | B10: 726.73B | C10: -0.71%
A11: Dec 29, 2017 | B11: 731.90B | C11: 34.00%
A12: Dec 30, 2016 | B12: 546.19B | C12: 2.08%
A13: Dec 31, 2015 | B13: 535.06B | C13: 48.64%
A14: Dec 31, 2014 | B14: 359.98B | C14: -3.95%
A15: Dec 31, 2013 | B15: 374.79B | C15: 61.85%
... A24: Dec 31, 2004 | B24: 52.77B | C24: 93.71%
A25: Source: https://stockanalysis.com/stocks/googl/market-cap/

Sheet Income statement
A1: Alphabet Inc. Class C (GOOG)
A2: $149.11
A5: Alphabet Inc. Class C
A6: GOOG 02079K107 BYY88Y7 NASDAQ Common stock
A7: Source: FactSet Fundamentals
B8: DEC '24 | C8: DEC '23 | D8: DEC '22 | E8: DEC '21 | F8: DEC '20 | G8: DEC '19 | H8: DEC '18 | I8: DEC '17 | J8: DEC '16 | K8: DEC '15 | L8: DEC '14 | M8: DEC '13 | N8: DEC '12 | O8: DEC '11 | P8: DEC '10 | Q8: DEC '09 | R8: DEC '08 | S8: DEC '07 | T8: DEC '06 | U8: DEC '05 | V8: DEC '04 | W8: DEC '03 | X8: DEC '02 | Y8: DEC '01
K9: Restate | L9: Restate
A10: Sales | B10: 349.81 | C10: 307.16 | D10: 280.88 | E10: 257.49 | F10: 182.35 | G10: 161.4 | H10: 136.96 | I10: 111.02 | J10: 89.73 | K10: 73.59 | L10: 65.83 | M10: 59.73 | N10: 49.96 | O10: 37.86 | P10: 29.12 | Q10: 23.33 | R10: 21.8 | S10: 16.59 | T10: 10.6 | U10: 6.14 | V10: 3.19 | W10: 1.47 | X10: 0.44 | Y10: 0.09
A11: Growth (%) | B11: 13.89 | C11: 9.36 | D11: 9.08 | E11: 41.21 | F11: 12.98 | G11: 17.85 | H11: 23.36 | I11: 23.73 | J11: 21.94 | K11: 11.79 | L11: 10.21 | M11: 19.56 | N11: 31.95 | O11: 30.03 | P11: 24.83 | Q11: 7.02 | R11: 31.35 | S11: 56.47 | T11: 72.76 | U11: 92.48 | V11: 117.56 | W11: 233.54 | X11: 408.54
A12: Cost of Goods Sold (COGS) incl. D&A | B12: 146.31 | C12: 132.85 | D12: 126.2 | E12: 110.94 | F12: 84.73 | G12: 71.9 | H12: 59.55 | I12: 45.58 | J12: 35.14 | K12: 28.16 | L12: 25.31 | M12: 25.82 | N12: 20.51 | O12: 13.19 | P12: 10.42 | Q12: 8.84 | R12: 8.62 | S12: 6.65 | T12: 4.23 | U12: 2.57 | V12: 1.46 | W12: 0.63 | X12: 0.13 | Y12: 0.01
A13: COGS excluding D&A | B13: 131 | C13: 120.91 | D13: 110.28 | E13: 98.5 | F13: 71.04 | G13: 60.12 | H13: 50.51 | I13: 38.67 | J13: 28.99 | K13: 23.1 | L13: 20.71 | M13: 21.89 | N13: 17.54 | O13: 11.34 | P13: 9.02 | Q13: 7.32 | R13: 7.12 | S13: 5.68 | T13: 3.65 | U13: 2.28 | V13: 1.31 | W13: 0.58 | X13: 0.11 | Y13: 0
A14: Depreciation & Amortization Expense | B14: 15.31 | C14: 11.95 | D14: 15.93 | E14: 12.44 | F14: 13.7 | G14: 11.78 | H14: 9.04 | I14: 6.92 | J14: 6.14 | K14: 5.06 | L14: 4.6 | M14: 3.94 | N14: 2.96 | O14: 1.85 | P14: 1.4 | Q14: 1.52 | R14: 1.5 | S14: 0.97 | T14: 0.57 | U14: 0.29 | V14: 0.15 | W14: 0.05 | X14: 0.02 | Y14: 0.01
A15: Depreciation | B15: 15.31 | C15: 11.95 | D15: 15.29 | E15: 11.56 | F15: 12.91 | G15: 10.86 | H15: 8.16 | I15: 6.1 | J15: 5.27 | K15: 4.13 | L15: 3.52 | M15: 2.78 | N15: 1.99 | O15: 1.4 | P15: 1.07 | Q15: 1.24 | R15: 1.21 | S15: 0.81 | T15: 0.49 | U15: 0.26 | V15: 0.13 | W15: 0.04 | X15: 0.02 | Y15: 0.01
A16: Amortization of Intangibles | B16: 0 | C16: 0 | D16: 0.64 | E16: 0.89 | F16: 0.79 | G16: 0.93 | H16: 0.87 | I16: 0.81 | J16: 0.88 | K16: 0.93 | L16: 1.08 | M16: 1.16 | N16: 0.97 | O16: 0.46 | P16: 0.33 | Q16: 0.28 | R16: 0.29 | S16: 0.16 | T16: 0.08 | U16: 0.04 | V16: 0.02 | W16: 0.01 | X16: 0 | Y16: 0
A17: Gross Income | B17: 203.5 | C17: 174.3 | D17: 154.67 | E17: 146.55 | F17: 97.62 | G17: 89.51 | H17: 77.41 | I17: 65.44 | J17: 54.6 | K17: 45.43 | L17: 40.52 | M17: 33.91 | N17: 29.45 | O17: 24.67 | P17: 18.7 | Q17: 14.48 | R17: 13.17 | S17: 9.94 | T17: 6.38 | U17: 3.57 | V17: 1.73 | W17: 0.84 | X17: 0.31 | Y17: 0.07
A18: Growth (%) | B18: 16.75 | C18: 12.69 | D18: 5.54 | E18: 50.12 | F18: 9.06 | G18: 15.63 | H18: 18.29 | I18: 19.87 | J18: 20.18 | K18: 12.12 | L18: 19.5 | M18: 15.12 | N18: 19.37 | O18: 31.94 | P18: 29.14 | Q18: 9.93 | R18: 32.47 | S18: 55.88 | T18: 78.86 | U18: 106 | V18: 106.12 | W18: 172.76 | X18: 326.6
A19: Margin (%) | B19: 58.18 | C19: 56.75 | D19: 55.07 | E19: 56.91 | F19: 53.53 | G19: 55.46 | H19: 56.52 | I19: 58.94 | J19: 60.84 | K19: 61.73 | L19: 61.55 | M19: 56.77 | N19: 58.96 | O19: 65.17 | P19: 64.22 | Q19: 62.08 | R19: 60.44 | S19: 59.93 | T19: 60.16 | U19: 58.11 | V19: 54.29 | W19: 57.31 | X19: 70.08 | Y19: 83.54
A20: SG&A Expense | B20: 91.32 | C20: 88.16 | D20: 81.79 | E20: 67.98 | F20: 56.57 | G20: 54.03 | H20: 45.88 | I20: 36.39 | J20: 31.42 | K20: 27.47 | L20: 23.81 | M20: 19.91 | N20: 16.33 | O20: 12.48 | P20: 8.52 | Q20: 6.49 | R20: 6.54 | S20: 4.86 | T20: 2.79 | U20: 1.44 | V20: 0.88 | W20: 0.5 | X20: 0.1 | Y20: 0.05
A21: Research & Development | B21: 49.33 | C21: 44.58 | D21: 39.5 | E21: 31.56 | F21: 27.57 | G21: 26.02 | H21: 21.42 | I21: 16.63 | J21: 13.95 | K21: 12.28 | L21: 9.83 | M21: 7.91 | N21: 6.59 | O21: 5.16 | P21: 3.76 | Q21: 2.84 | R21: 2.79 | S21: 2.12 | T21: 1.22 | U21: 0.46 | V21: 0.21 | W21: 0.09 | X21: 0.03 | Y21: 0.02
A22: Other SG&A | B22: 42 | C22: 43.58 | D22: 42.29 | E22: 36.42 | F22: 29 | G22: 28.02 | H22: 24.46 | I22: 19.77 | J22: 17.47 | K22: 15.18 | L22: 13.98 | M22: 12 | N22: 9.74 | O22: 7.31 | P22: 4.76 | Q22: 3.65 | R22: 3.75 | S22: 2.74 | T22: 1.57 | U22: 0.98 | V22: 0.66 | W22: 0.41 | X22: 0.07 | Y22: 0.03
A23: Other Operating Expense | B23: 0 | C23: 0 | D23: 0 | E23: 0 | F23: 0 | G23: 0 | H23: 0 | I23: 0 | J23: 0 | K23: 0 | L23: 0 | M23: 0 | N23: 0 | O23: 0 | P23: 0 | Q23: 0 | R23: 0 | S23: 0 | T23: 0 | U23: 0.09 | V23: 0 | W23: 0 | X23: 0.02 | Y23: 0.01
A24: EBIT (Operating Income) | B24: 112.18 | C24: 86.14 | D24: 72.88 | E24: 78.57 | F24: 41.05 | G24: 35.47 | H24: 31.53 | I24: 29.05 | J24: 23.18 | K24: 17.96 | L24: 16.7 | M24: 13.99 | N24: 13.12 | O24: 12.2 | P24: 10.18 | Q24: 7.99 | R24: 6.63 | S24: 5.08 | T24: 3.59 | U24: 2.04 | V24: 0.85 | W24: 0.34 | X24: 0.19 | Y24: 0.01
A25: Growth (%) | B25: 30.22 | C25: 18.2 | D25: -7.23 | E25: 91.4 | F25: 15.71 | G25: 12.5 | H25: 8.54 | I25: 25.34 | J25: 29.04 | K25: 7.53 | L25: 19.36 | M25: 6.67 | N25: 7.54 | O25: 19.86 | P25: 27.42 | Q25: 20.44 | R25: 30.44 | S25: 41.6 | T25: 76.08 | U25: 139.2 | V25: 148.95 | W25: 83.66 | X25: 1599.73
A26: Margin (%) | B26: 32.07 | C26: 28.05 | D26: 25.95 | E26: 30.51 | F26: 22.51 | G26: 21.98 | H26: 23.02 | I26: 26.17 | J26: 25.83 | K26: 24.41 | L26: 25.37 | M26: 23.43 | N26: 26.26 | O26: 32.22 | P26: 34.95 | Q26: 34.24 | R26: 30.43 | S26: 30.64 | T26: 33.86 | U26: 33.22 | V26: 26.73 | W26: 23.36 | X26: 42.43 | Y26: 12.69
A27: Nonoperating Income - Net | B27: 3.68 | C27: 2.03 | D27: 2.11 | E27: 2.12 | F27: 2.01 | G27: 3.06 | H27: 4.4 | I27: 1.11 | J27: 1.47 | K27: 2.1 | L27: 1.21 | M27: 0.6 | N27: 1.46 | O27: 1.12 | P27: 0.98 | Q27: 0.47 | R27: 0.32 | S27: 0.59 | T27: 0.46 | U27: 0.13 | V27: 0.01 | W27: 0.01 | X27: 0 | Y27: 0
A28: Nonoperating Interest Income | B28: 4.48 | C28: 3.87 | D28: 2.17 | E28: 1.5 | F28: 1.87 | G28: 2.43 | H28: 1.88 | I28: 1.31 | J28: 1.22 | K28: 1 | L28: 0.75 | M28: 0.79 | N28: 0.71 | O28: 0.81 | P28: 0.58 | Q28: 0.23 | R28: 0.39 | S28: 0.56 | T28: 0.41 | U28: 0.12 | V28: 0.02 | W28: 0 | X28: 0 | Y28: 0
A29: Equity in Earnings of Affiliates | B29: -0.19 | C29: -0.63 | D29: -0.34 | E29: 0.33 | F29: 0.4 | G29: 0.39 | H29: -0.12 | I29: -0.16 | J29: -0.2 | K29: -0.23 | N29: 0 | O29: 0 | P29: 0 | Q29: 0 | R29: 0 | S29: 0 | T29: 0 | U29: 0 | W29: 0 | X29: 0 | Y29: 0
A30: Reserves Increase (Decrease) | B30: 0 | C30: 0 | D30: 0 | E30: 0 | F30: 0 | G30: 0 | H30: 0 | I30: 0 | J30: 0 | K30: 0 | L30: 0 | M30: 0 | N30: 0 | O30: 0 | P30: 0 | Q30: 0 | R30: 0 | S30: 0 | T30: 0 | U30: 0 | V30: 0 | W30: 0 | X30: 0 | Y30: 0
A31: Other Income (Expense) | B31: -0.61 | C31: -1.2 | D31: 0.27 | E31: 0.28 | F31: -0.26 | G31: 0.24 | H31: 2.64 | I31: -0.05 | J31: 0.45 | K31: 1.32 | L31: 0.47 | M31: -0.19 | N31: 0.74 | O31: 0.31 | P31: 0.41 | Q31: 0.24 | R31: -0.07 | S31: 0.03 | T31: 0.05 | U31: 0 | V31: -0.01 | W31: 0 | X31: 0 | Y31: 0
A32: Interest Expense | B32: 0.27 | C32: 0.31 | D32: 0.36 | E32: 0.35 | F32: 0.14 | G32: 0.1 | H32: 0.11 | I32: 0.11 | J32: 0.12 | K32: 0.1 | L32: 0.1 | M32: 0.08 | N32: 0.08 | O32: 0.06 | P32: 0 | Q32: 0 | R32: 0 | S32: 0 | T32: 0 | U32: 0 | V32: 0 | W32: 0 | X32: 0 | Y32: 0
A33: Gross Interest Expense | B33: 0.46 | C33: 0.49 | D33: 0.49 | E33: 0.51 | F33: 0.35 | G33: 0.27 | H33: 0.21 | I33: 0.16 | J33: 0.12 | K33: 0.1 | L33: 0.1 | M33: 0.08 | N33: 0.08 | O33: 0.06 | P33: 0 | Q33: 0 | R33: 0 | S33: 0 | T33: 0 | U33: 0 | V33: 0 | W33: 0 | X33: 0 | Y33: 0
A34: Interest Capitalized | B34: 0.19 | C34: 0.18 | D34: 0.13 | E34: 0.16 | F34: 0.22 | G34: 0.17 | H34: 0.09 | I34: 0.05 | J34: 0 | K34: 0 | L34: 0 | M34: 0 | N34: 0 | O34: 0 | P34: 0 | Q34: 0 | R34: 0 | S34: 0 | T34: 0 | U34: 0 | V34: 0 | W34: 0 | Y34: 0
A35: Unusual Expense - Net | B35: -4.22 | C35: 2.15 | D35: 3.31 | E35: -10.4 | F35: -5.16 | G35: -1.2 | H35: 0.9 | I35: 2.86 | J35: 0.38 | K35: 0.3 | L35: 0.56 | M35: 0.01 | N35: 1.1 | O35: 0.94 | P35: 0.37 | Q35: 0.08 | R35: 1.09 | S35: 0 | T35: 0.04 | U35: 0.02 | V35: 0.21
A36: Impairments | L36: 0.38 | M36: 0 | N36: 0 | O36: 0.11 | P36: 0 | Q36: 0 | R36: 1.09
A37: Other Intangibles | B37: 0 | C37: 0 | D37: 0 | E37: 0 | F37: 0 | G37: 0 | H37: 0 | I37: 0 | J37: 0 | K37: 0 | L37: 0.38 | M37: 0 | N37: 0 | O37: 0 | P37: 0 | Q37: 0 | R37: 0 | S37: 0 | T37: 0 | U37: 0
A38: Financial Fixed Assets | M38: 0 | N38: 0 | O38: 0.11 | P38: 0 | Q38: 0 | R38: 1.09
A39: Restructuring Expense | B39: 0 | C39: 2.09 | D39: 0 | E39: 0 | F39: 0 | G39: 0 | H39: 0 | I39: 0 | J39: 0 | K39: 0 | L39: 0 | M39: 0.12 | N39: 0.58 | O39: 0 | P39: 0 | Q39: 0 | R39: 0 | S39: 0 | T39: 0 | U39: 0 | V39: 0 | W39: 0 | X39: 0 | Y39: 0
A40: Legal Claim Expense | E40: 0 | F40: 0 | G40: 1.7 | H40: 5.07 | I40: 2.74 | M40: 0 | N40: 0 | O40: 0.5 | T40: 0.03 | U40: 0 | V40: 0.2
A41: Unrealized Valuation Gain/Loss | B41: 4.22 | C41: -0.07 | D41: -3.31 | E41: 10.4 | F41: 5.16 | G41: 2.89 | H41: 4.17 | I41: -0.12 | J41: -0.38 | K41: -0.3 | L41: -0.18 | M41: 0.11 | N41: -0.53 | O41: -0.33 | P41: -0.37 | Q41: -0.08
A42: Investments | B42: 3.53 | C42: -0.3 | D42: -3.01 | E42: 11.18 | F42: 4.25 | G42: 2.95 | H42: 4
A43: Hedges/Derivatives | B43: 0.7 | C43: 0.23 | D43: -0.29 | E43: -0.79 | F43: 0.91 | G43: -0.06 | H43: 0.17 | I43: -0.12 | J43: -0.38 | K43: -0.3 | L43: -0.28 | M43: 0.11 | N43: -0.53 | O43: -0.33 | P43: -0.37 | Q43: -0.08
A44: Other Intangibles | L44: 0.1
A45: Excpl Chrgs - Others | S45: 0 | T45: 0.01 | U45: 0.02 | V45: 0.01
A46: Acquired In-Process R&D | T46: 0.01 | U46: 0.02
A47: Pretax Income | B47: 119.82 | C47: 85.72 | D47: 71.33 | E47: 90.73 | F47: 48.08 | G47: 39.63 | H47: 34.91 | I47: 27.19 | J47: 24.15 | K47: 19.65 | L47: 17.26 | M47: 14.5 | N47: 13.39 | O47: 12.33 | P47: 10.8 | Q47: 8.38 | R47: 5.85 | S47: 5.67 | T47: 4.01 | U47: 2.14 | V47: 0.65 | W47: 0.35 | X47: 0.18 | Y47: 0.01
A48: Growth (%) | B48: 39.78 | C48: 20.17 | D48: -21.39 | E48: 88.71 | F48: 21.34 | G48: 13.5 | H48: 28.39 | I48: 12.6 | J48: 22.89 | K48: 13.86 | L48: 19.06 | M48: 8.29 | N48: 8.6 | O48: 14.17 | P48: 28.81 | Q48: 43.18 | R48: 3.17 | S48: 41.46 | T48: 87.29 | U48: 229.37 | V48: 87.57 | W48: 87.47 | X48: 1736.66
A49: Margin (%) | B49: 34.25 | C49: 27.91 | D49: 25.39 | E49: 35.24 | F49: 26.37 | G49: 24.55 | H49: 25.49 | I49: 24.49 | J49: 26.91 | K49: 26.7 | L49: 26.22 | M49: 24.27 | N49: 26.79 | O49: 32.56 | P49: 37.08 | Q49: 35.93 | R49: 26.86 | S49: 34.19 | T49: 37.82 | U49: 34.89 | V49: 20.39 | W49: 23.65 | X49: 42.07 | Y49: 11.65
A50: Income Taxes | B50: 19.7 | C50: 11.92 | D50: 11.36 | E50: 14.7 | F50: 7.81 | G50: 5.28 | H50: 4.18 | I50: 14.53 | J50: 4.67 | K50: 3.3 | L50: 3.64 | M50: 2.28 | N50: 2.6 | O50: 2.59 | P50: 2.29 | Q50: 1.86 | R50: 1.63 | S50: 1.47 | T50: 0.93 | U50: 0.68 | V50: 0.25 | W50: 0.24 | X50: 0.09 | Y50: 0
A51: Income Taxes - Current Domestic | B51: 22.49 | C51: 17.13 | D51: 17.12 | E51: 10.13 | F51: 4.79 | G51: 2.42 | H51: 2.15 | I51: 12.61 | J51: 3.83 | K51: 2.84 | L51: 2.87 | M51: 1.96 | N51: 2.51 | O51: 2 | P51: 2.12 | Q51: 1.98 | R51: 1.82 | S51: 1.58 | T51: 1 | U51: 0.65 | V51: 0.28 | W51: 0.24 | X51: 0.09 | Y51: 0.01
A52: Income Taxes - Current Foreign | B52: 2.47 | C52: 2.53 | D52: 2.43 | E52: 2.69 | F52: 1.69 | G52: 2.71 | H52: 1.25 | I52: 1.75 | J52: 0.97 | K52: 0.72 | L52: 0.77 | M52: 0.77 | N52: 0.36 | O52: 0.25 | P52: 0.17 | Q52: 0.15 | R52: 0.09 | S52: 0.05 | T52: 0.03 | U52: 0.01 | V52: 0 | W52: 0 | X52: 0 | Y52: 0
A53: Income Taxes - Deferred Domestic | B53: -5.35 | C53: -7.48 | D53: -8.05 | E53: 2.02 | F53: 1.55 | G53: 0.29 | H53: 0.91 | I53: 0.22 | J53: -0.07 | K53: -0.24 | L53: 0.04 | M53: -0.43 | N53: -0.35 | O53: 0.34 | P53: 0.02 | Q53: -0.26 | R53: -0.26 | S53: -0.16 | T53: -0.1 | U53: 0.02 | V53: -0.03 | W53: 0 | X53: -0.01 | Y53: 0
A54: Income Taxes - Deferred Foreign | B54: 0.09 | C54: -0.25 | D54: -0.15 | E54: -0.14 | F54: -0.22 | G54: -0.14 | H54: -0.13 | I54: -0.04 | J54: -0.05 | K54: -0.02 | L54: -0.04 | M54: -0.03 | N54: 0.07 | O54: 0 | P54: -0.01 | Q54: -0.01 | R54: -0.02 | S54: 0 | T54: 0 | U54: 0 | V54: 0 | W54: 0 | X54: 0 | Y54: 0
A55: Other After Tax Adjustments | B55: 0 | C55: 0 | D55: 0 | E55: 0 | F55: 0 | G55: 0 | H55: 0 | I55: 0 | J55: 0 | K55: -0.52 | L55: 0 | M55: 0 | N55: 0 | O55: 0 | P55: 0 | Q55: 0 | R55: 0 | S55: 0 | T55: 0 | U55: 0 | V55: 0 | W55: 0 | X55: 0 | Y55: 0
A56: Consolidated Net Income | B56: 100.12 | C56: 73.8 | D56: 59.97 | E56: 76.03 | F56: 40.27 | G56: 34.34 | H56: 30.74 | I56: 12.66 | J56: 19.48 | K56: 15.83 | L56: 13.62 | M56: 12.21 | N56: 10.79 | O56: 9.74 | P56: 8.51 | Q56: 6.52 | R56: 4.23 | S56: 4.2 | T56: 3.08 | U56: 1.47 | V56: 0.4 | W56: 0.11 | X56: 0.1 | Y56: 0.01
A57: Growth (%) | B57: 35.67 | C57: 23.05 | D57: -21.12 | E57: 88.81 | F57: 17.26 | G57: 11.74 | H57: 142.74 | I57: -34.99 | J57: 23.08 | K57: 16.2 | L57: 11.51 | M57: 13.22 | N57: 10.79 | O57: 14.49 | P57: 30.44 | Q57: 54.26 | R57: 0.55 | S57: 36.6 | T57: 110.01 | U57: 267.16 | V57: 277.78 | W57: 6.01 | X57: 1326.71
A58: Margin (%) | B58: 28.62 | C58: 24.03 | D58: 21.35 | E58: 29.53 | F58: 22.08 | G58: 21.28 | H58: 22.44 | I58: 11.4 | J58: 21.71 | K58: 21.51 | L58: 20.69 | M58: 20.45 | N58: 21.59 | O58: 25.72 | P58: 29.21 | Q58: 27.95 | R58: 19.39 | S58: 25.33 | T58: 29.02 | U58: 23.87 | V58: 12.51 | W58: 7.21 | X58: 22.67 | Y58: 8.08
A59: Net Income | B59: 100.12 | C59: 73.8 | D59: 59.97 | E59: 76.03 | F59: 40.27 | G59: 34.34 | H59: 30.74 | I59: 12.66 | J59: 19.48 | K59: 15.83 | L59: 13.62 | M59: 12.21 | N59: 10.79 | O59: 9.74 | P59: 8.51 | Q59: 6.52 | R59: 4.23 | S59: 4.2 | T59: 3.08 | U59: 1.47 | V59: 0.4 | W59: 0.11 | X59: 0.1 | Y59: 0.01
A60: Growth (%) | B60: 35.67 | C60: 23.05 | D60: -21.12 | E60: 88.81 | F60: 17.26 | G60: 11.74 | H60: 142.74 | I60: -34.99 | J60: 23.08 | K60: 16.2 | L60: 11.51 | M60: 13.22 | N60: 10.79 | O60: 14.49 | P60: 30.44 | Q60: 54.26 | R60: 0.55 | S60: 36.6 | T60: 110.01 | U60: 267.16 | V60: 277.78 | W60: 6.01 | X60: 1326.71
A61: Margin (%) | B61: 28.62 | C61: 24.03 | D61: 21.35 | E61: 29.53 | F61: 22.08 | G61: 21.28 | H61: 22.44 | I61: 11.4 | J61: 21.71 | K61: 21.51 | L61: 20.69 | M61: 20.45 | N61: 21.59 | O61: 25.72 | P61: 29.21 | Q61: 27.95 | R61: 19.39 | S61: 25.33 | T61: 29.02 | U61: 23.87 | V61: 12.51 | W61: 7.21 | X61: 22.67 | Y61: 8.08
A62: Discontinued Operations | B62: 0 | C62: 0 | D62: 0 | E62: 0 | F62: 0 | G62: 0 | H62: 0 | I62: 0 | J62: 0 | K62: 0 | L62: -0.22 | M62: -0.05 | N62: -0.05 | O62: 0 | P62: 0 | Q62: 0 | R62: 0 | S62: 0 | T62: 0 | U62: 0 | V62: 0 | W62: 0 | X62: 0 | Y62: 0
A63: Net Income available to Common | B63: 100.12 | C63: 73.8 | D63: 59.97 | E63: 76.03 | F63: 40.27 | G63: 34.34 | H63: 30.74 | I63: 12.66 | J63: 19.48 | K63: 15.83 | L63: 13.4 | M63: 12.16 | N63: 10.74 | O63: 9.74 | P63: 8.51 | Q63: 6.52 | R63: 4.23 | S63: 4.2 | T63: 3.08 | U63: 1.47 | V63: 0.4 | W63: 0.11 | X63: 0.1 | Y63: 0.01
A64: Per Share
A65: EPS (recurring) | B65: 7.81 | C65: 5.92 | D65: 4.73 | E65: 5.07 | F65: 2.67 | G65: 2.4 | H65: 2.23 | I65: 1.04 | J65: 1.41 | K65: 1.16 | L65: 1
A66: EPS (basic) | B66: 8.13 | C66: 5.84 | D66: 4.59 | E66: 5.69 | F66: 2.96 | G66: 2.48 | H66: 2.21 | I66: 0.91 | J66: 1.42 | K66: 1.16 | L66: 0.99
A67: Basic Shares Outstanding (M) | B67: 12319 | C67: 12630 | D67: 13063 | E67: 13353 | F67: 13616.32 | G67: 13851.92 | H67: 13902.8 | I67: 13858.02 | J67: 13755.56 | K67: 13692.52 | L67: 13555.82
A68: Total Shares Outstanding (M) | B68: 12211 | C68: 12460 | D68: 12849 | E68: 13242.42 | F68: 13504.44 | G68: 13766.7 | H68: 13911.12 | I68: 13895.66 | J68: 13825.86 | K68: 13746.96 | L68: 13603.44 | M68: 13420.3 | N68: 13186.4 | O68: 12983.22 | P68: 12839.61 | Q68: 12698.59 | R68: 12592.37 | S68: 12504.58 | T68: 12347.95 | U68: 11696.21 | V68: 10970.26 | W68: 10926.06 | X68: 9755
A69: EPS (diluted) | B69: 8.04 | C69: 5.8 | D69: 4.56 | E69: 5.61 | F69: 2.93 | G69: 2.46 | H69: 2.19 | I69: 0.9 | J69: 1.39 | K69: 1.14 | L69: 0.97
A70: Diluted Shares Outstanding (M) | B70: 12447 | C70: 12722 | D70: 13159 | E70: 13553.48 | F70: 13740.56 | G70: 13971.12 | H70: 14065.7 | I70: 14071.68 | J70: 13974.12 | K70: 13858.6 | L70: 13779.13
A71: Total Shares Outstanding (M) | B71: 12211 | C71: 12460 | D71: 12849 | E71: 13242.42 | F71: 13504.44 | G71: 13766.7 | H71: 13911.12 | I71: 13895.66 | J71: 13825.86 | K71: 13746.96 | L71: 13603.44 | M71: 13420.3 | N71: 13186.4 | O71: 12983.22 | P71: 12839.61 | Q71: 12698.59 | R71: 12592.37 | S71: 12504.58 | T71: 12347.95 | U71: 11696.21 | V71: 10970.26 | W71: 10926.06 | X71: 9755
A72: Earnings Persistence | B72: 79.76 | C72: 85.67 | D72: 81.47 | E72: 78.61 | F72: 83.21 | G72: 77.51 | H72: 76.09 | I72: 85.79 | J72: 79.3 | K72: 76.94 | L72: 72.9 | M72: 78.3 | N72: 68.52 | O72: 63.67 | P72: 67.24 | Q72: 74.8 | R72: 74.11 | S72: 71.1 | T72: 38.83 | U72: 41.78 | V72: 34.64 | W72: 57.26
A73: Dividends per Share | B73: 0.6 | C73: 0 | D73: 0 | E73: 0 | F73: 0 | G73: 0 | H73: 0 | I73: 0 | J73: 0 | K73: 0 | L73: 0 | M73: 0 | N73: 0 | O73: 0 | P73: 0 | Q73: 0 | R73: 0 | S73: 0 | T73: 0 | U73: 0 | V73: 0
A74: Payout Ratio | B74: 7.46 | C74: 0 | D74: 0 | E74: 0 | F74: 0 | G74: 0 | H74: 0 | I74: 0 | J74: 0 | K74: 0 | L74: 0 | M74: 0 | N74: 0 | O74: 0 | P74: 0 | Q74: 0 | R74: 0 | S74: 0 | T74: 0 | U74: 0 | V74: 0
A75: EBITDA
A76: EBITDA | B76: 127.49 | C76: 98.09 | D76: 88.81 | E76: 91.01 | F76: 54.74 | G76: 47.25 | H76: 40.57 | I76: 35.97 | J76: 29.32 | K76: 23.02 | L76: 21.31 | M76: 17.93 | N76: 16.08 | O76: 14.05 | P76: 11.57 | Q76: 9.51 | R76: 8.13 | S76: 6.05 | T76: 4.16 | U76: 2.33 | V76: 1 | W76: 0.39 | X76: 0.2 | Y76: 0.02
A77: EBIT | B77: 112.18 | C77: 86.14 | D77: 72.88 | E77: 78.57 | F77: 41.05 | G77: 35.47 | H77: 31.53 | I77: 29.05 | J77: 23.18 | K77: 17.96 | L77: 16.7 | M77: 13.99 | N77: 13.12 | O77: 12.2 | P77: 10.18 | Q77: 7.99 | R77: 6.63 | S77: 5.08 | T77: 3.59 | U77: 2.04 | V77: 0.85 | W77: 0.34 | X77: 0.19 | Y77: 0.01
A78: Depreciation & Amortization Expense | B78: 15.31 | C78: 11.95 | D78: 15.93 | E78: 12.44 | F78: 13.7 | G78: 11.78 | H78: 9.04 | I78: 6.92 | J78: 6.14 | K78: 5.06 | L78: 4.6 | M78: 3.94 | N78: 2.96 | O78: 1.85 | P78: 1.4 | Q78: 1.52 | R78: 1.5 | S78: 0.97 | T78: 0.57 | U78: 0.29 | V78: 0.15 | W78: 0.05 | X78: 0.02 | Y78: 0.01
A79: All figures in billions of U.S. Dollar except per share and labeled items.

Sheet Key financial items
A1: Alphabet Inc. Class C (GOOG)
A2: $149.14
A5: Alphabet Inc. Class C
A6: GOOG 02079K107 BYY88Y7 NASDAQ Common stock
A7: Source: FactSet Fundamentals
B8: DEC '24 | C8: DEC '23 | D8: DEC '22 | E8: DEC '21 | F8: DEC '20 | G8: DEC '19 | H8: DEC '18 | I8: DEC '17 | J8: DEC '16 | K8: DEC '15 | L8: DEC '14 | M8: DEC '13 | N8: DEC '12 | O8: DEC '11 | P8: DEC '10 | Q8: DEC '09 | R8: DEC '08 | S8: DEC '07 | T8: DEC '06 | U8: DEC '05 | V8: DEC '04 | W8: DEC '03 | X8: DEC '02 | Y8: DEC '01
K9: Restate | L9: Restate
A10: Income Statement
A11: Sales | B11: 349.81 | C11: 307.16 | D11: 280.88 | E11: 257.49 | F11: 182.35 | G11: 161.4 | H11: 136.96 | I11: 111.02 | J11: 89.73 | K11: 73.59 | L11: 65.83 | M11: 59.73 | N11: 49.96 | O11: 37.86 | P11: 29.12 | Q11: 23.33 | R11: 21.8 | S11: 16.59 | T11: 10.6 | U11: 6.14 | V11: 3.19 | W11: 1.47 | X11: 0.44 | Y11: 0.09
A12: Gross Income | B12: 203.5 | C12: 174.3 | D12: 154.67 | E12: 146.55 | F12: 97.62 | G12: 89.51 | H12: 77.41 | I12: 65.44 | J12: 54.6 | K12: 45.43 | L12: 40.52 | M12: 33.91 | N12: 29.45 | O12: 24.67 | P12: 18.7 | Q12: 14.48 | R12: 13.17 | S12: 9.94 | T12: 6.38 | U12: 3.57 | V12: 1.73 | W12: 0.84 | X12: 0.31 | Y12: 0.07
A13: EBIT | B13: 112.18 | C13: 86.14 | D13: 72.88 | E13: 78.57 | F13: 41.05 | G13: 35.47 | H13: 31.53 | I13: 29.05 | J13: 23.18 | K13: 17.96 | L13: 16.7 | M13: 13.99 | N13: 13.12 | O13: 12.2 | P13: 10.18 | Q13: 7.99 | R13: 6.63 | S13: 5.08 | T13: 3.59 | U13: 2.04 | V13: 0.85 | W13: 0.34 | X13: 0.19 | Y13: 0.01
A14: EBITDA | B14: 127.49 | C14: 98.09 | D14: 88.81 | E14: 91.01 | F14: 54.74 | G14: 47.25 | H14: 40.57 | I14: 35.97 | J14: 29.32 | K14: 23.02 | L14: 21.31 | M14: 17.93 | N14: 16.08 | O14: 14.05 | P14: 11.57 | Q14: 9.51 | R14: 8.13 | S14: 6.05 | T14: 4.16 | U14: 2.33 | V14: 1 | W14: 0.39 | X14: 0.2 | Y14: 0.02
A15: Net Income | B15: 100.12 | C15: 73.8 | D15: 59.97 | E15: 76.03 | F15: 40.27 | G15: 34.34 | H15: 30.74 | I15: 12.66 | J15: 19.48 | K15: 15.83 | L15: 13.62 | M15: 12.21 | N15: 10.79 | O15: 9.74 | P15: 8.51 | Q15: 6.52 | R15: 4.23 | S15: 4.2 | T15: 3.08 | U15: 1.47 | V15: 0.4 | W15: 0.11 | X15: 0.1 | Y15: 0.01
A16: Balance Sheet
A17: Cash & Short-Term Investments | B17: 95.66 | C17: 110.92 | D17: 113.76 | E17: 139.65 | F17: 136.69 | G17: 119.68 | H17: 109.14 | I17: 101.87 | J17: 86.33 | K17: 73.07 | L17: 64.4 | M17: 58.72 | N17: 48.09 | O17: 44.63 | P17: 34.98 | Q17: 24.48 | R17: 15.85 | S17: 14.22 | T17: 11.24 | U17: 8.03 | V17: 2.14 | W17: 0.33 | X17: 0.15 | Y17: 0.03
A18: Total Assets | B18: 450.26 | C18: 402.39 | D18: 365.26 | E18: 359.27 | F18: 319.62 | G18: 275.91 | H18: 232.79 | I18: 197.3 | J18: 167.5 | K18: 147.46 | L18: 129.19 | M18: 110.92 | N18: 93.8 | O18: 72.57 | P18: 57.85 | Q18: 40.5 | R18: 31.77 | S18: 25.34 | T18: 18.47 | U18: 10.27 | V18: 3.3 | W18: 0.88 | X18: 0.29 | Y18: 0.08
A19: Total Debt | B19: 28.14 | C19: 29.87 | D19: 29.98 | E19: 28.51 | F19: 27.87 | G19: 15.97 | H19: 4.01 | I19: 3.97 | J19: 3.94 | K19: 5.22 | L19: 5.24 | M19: 5.25 | N19: 5.54 | O19: 4.2 | P19: 3.47 | Q19: 0 | R19: 0 | S19: 0 | T19: 0 | U19: 0 | V19: 0 | W19: 0.01 | X19: 0.01
A20: Net Debt | B20: -67.52 | C20: -81.05 | D20: -83.79 | E20: -111.14 | F20: -108.82 | G20: -103.71 | H20: -105.13 | I20: -97.9 | J20: -82.4 | K20: -67.85 | L20: -59.16 | M20: -53.47 | N20: -42.55 | O20: -40.42 | P20: -31.51 | Q20: -24.48 | R20: -15.85 | S20: -14.22 | T20: -11.24 | U20: -8.03 | V20: -2.14 | W20: -0.33 | X20: -0.14
A21: Total Liabilities | B21: 125.17 | C21: 119.01 | D21: 109.12 | E21: 107.63 | F21: 97.07 | G21: 74.47 | H21: 55.16 | I21: 44.79 | J21: 28.46 | K21: 27.13 | L21: 25.33 | M21: 23.61 | N21: 22.08 | O21: 14.43 | P21: 11.61 | Q21: 4.49 | R21: 3.53 | S21: 2.65 | T21: 1.43 | U21: 0.85 | V21: 0.37 | W21: 0.27 | X21: 0.1 | Y21: 0.03
A22: Total Shareholders' Equity | B22: 325.08 | C22: 283.38 | D22: 256.14 | E22: 251.64 | F22: 222.54 | G22: 201.44 | H22: 177.63 | I22: 152.5 | J22: 139.04 | K22: 120.33 | L22: 103.86 | M22: 87.31 | N22: 71.72 | O22: 58.15 | P22: 46.24 | Q22: 36 | R22: 28.24 | S22: 22.69 | T22: 17.04 | U22: 9.42 | V22: 2.93 | W22: 0.61 | X22: 0.19 | Y22: 0.05
A23: Cash Flow
A24: Net Operating Cash Flow | B24: 125.3 | C24: 101.75 | D24: 91.5 | E24: 91.65 | F24: 65.12 | G24: 54.52 | H24: 47.97 | I24: 37.09 | J24: 36.04 | K24: 26.57 | L24: 22.38 | M24: 18.66 | N24: 16.62 | O24: 14.57 | P24: 11.08 | Q24: 9.32 | R24: 7.85 | S24: 5.78 | T24: 3.58 | U24: 2.46 | V24: 0.98 | W24: 0.4 | X24: 0.16 | Y24: 0.03
A25: Capital Expenditures | B25: -52.54 | C25: -32.25 | D25: -31.49 | E25: -24.64 | F25: -22.28 | G25: -23.55 | H25: -25.14 | I25: -13.18 | J25: -10.21 | K25: -9.95 | L25: -10.96 | M25: -7.36 | N25: -3.27 | O25: -3.44 | P25: -4.02 | Q25: -0.81 | R25: -2.36 | S25: -2.4 | T25: -1.9 | U25: -0.84 | V25: -0.36 | W25: -0.18 | X25: -0.04 | Y25: -0.01
A26: Net Investing Cash Flow | B26: -45.54 | C26: -27.06 | D26: -20.3 | E26: -35.52 | F26: -32.77 | G26: -29.49 | H26: -28.5 | I26: -31.4 | J26: -31.17 | K26: -23.71 | L26: -21.06 | M26: -13.68 | N26: -13.06 | O26: -19.04 | P26: -10.68 | Q26: -8.02 | R26: -5.32 | S26: -3.68 | T26: -6.9 | U26: -3.36 | V26: -1.9 | W26: -0.31 | X26: -0.11 | Y26: -0.03
A27: Net Financing Cash Flow | B27: -79.73 | C27: -72.09 | D27: -69.76 | E27: -61.36 | F27: -24.41 | G27: -23.21 | H27: -13.18 | I27: -8.3 | J27: -8.33 | K27: -4.23 | L27: -1.44 | M27: -0.86 | N27: 1.23 | O27: 0.81 | P27: 3.05 | Q27: 0.23 | R27: 0.09 | S27: 0.4 | T27: 2.97 | U27: 4.37 | V27: 1.19 | W27: 0.01 | X27: -0.01 | Y27: 0
A28: Free Cash Flow | B28: 72.76 | C28: 69.5 | D28: 60.01 | E28: 67.01 | F28: 42.84 | G28: 30.97 | H28: 22.83 | I28: 23.91 | J28: 25.82 | K28: 16.62 | L28: 11.42 | M28: 11.3 | N28: 13.35 | O28: 11.13 | P28: 7.06 | Q28: 8.51 | R28: 5.49 | S28: 3.37 | T28: 1.68 | U28: 1.62 | V28: 0.66 | W28: 0.22 | X28: 0.12 | Y28: 0.02
A29: Supplemental
A30: Stock Option Comp Exp (Net of Tax) | B30: 18.2 | C30: 17.6 | D30: 15.6 | E30: 12.6 | F30: 10.7 | G30: 10.79 | H30: 7.25 | I30: 6.07 | J30: 5.31 | K30: 3.6 | L30: 3.38 | M30: 1.96 | N30: 1.59 | O30: 1.18 | P30: 0.83 | Q30: 0.7 | R30: 0.67 | S30: 0.52 | T30: 0.27 | U30: 0.12 | V30: 0.17 | W30: 0.21
A31: Operating Lease Commitments | B31: 17.04 | C31: 17.68 | D31: 17.44 | E31: 15.46 | F31: 15.09 | G31: 10.1 | H31: 10.05 | I31: 8.75 | J31: 7.94 | L31: 6.25 | M31: 4.13 | N31: 3.7 | O31: 2.95 | P31: 2.39 | Q31: 2.54 | R31: 2.96 | S31: 2.28 | T31: 1.21 | U31: 0.69 | V31: 0.24 | W31: 0.15
A32: Long Term Debt Maturities | B32: 1.23 | C32: 1.36 | D32: 0.3 | E32: 0.11 | F32: 1.1 | G32: 0 | H32: 0 | I32: 0 | J32: 0 | K32: 1.23 | L32: 0.01 | M32: 1.01 | N32: 0 | O32: 0 | P32: 0 | Q32: 0 | R32: 0 | S32: 0 | T32: 0 | U32: 0 | V32: 0 | W32: 0 | X32: 0
A33: Audit Information
A34: Fees (M) | C34: 41.4 | D34: 41.22 | E34: 34.38 | F34: 29.85 | G34: 29.85 | H34: 27.45 | I34: 25.99 | J34: 20.96 | K34: 20.68 | L34: 20.86 | M34: 20.06 | N34: 14.29 | O34: 13.01 | R34: 12.03 | S34: 9.67 | T34: 8 | U34: 4.94 | V34: 3.76
A35: Opinion | B35: Unqualified | C35: Unqualified | D35: Unqualified | E35: Unqualified | F35: Unqualified | G35: Unqualified | H35: Unqualified | I35: Unqualified | J35: Unqualified | K35: Unqualified | L35: Unqualified | M35: Unqualified | N35: Unqualified | O35: Unqualified | P35: Unqualified | Q35: Unqualified | R35: Unqualified | S35: Unqualified | T35: Unqualified | U35: Unqualified | V35: Unqualified | W35: Unqualified | X35: Unqualified | Y35: Unqualified
A36: All figures in billions of U.S. Dollar except labeled items.

Sheet Ratios Factset
A1: Alphabet Inc. Class A (GOOGL)
A2: $147.50
A5: Alphabet Inc. Class A
A6: GOOGL 02079K305 BYVY8G0 NASDAQ Common stock
A7: Source: FactSet Fundamentals
B8: DEC '24 | C8: DEC '23 | D8: DEC '22 | E8: DEC '21 | F8: DEC '20 | G8: DEC '19 | H8: DEC '18 | I8: DEC '17 | J8: DEC '16 | K8: DEC '15 | L8: DEC '14 | M8: DEC '13 | N8: DEC '12 | O8: DEC '11 | P8: DEC '10 | Q8: DEC '09 | R8: DEC '08 | S8: DEC '07 | T8: DEC '06 | U8: DEC '05 | V8: DEC '04 | W8: DEC '03 | X8: DEC '02 | Y8: DEC '01
K9: Restate | L9: Restate
A10: Profitability
A11: Gross Margin | B11: 58,18 | C11: 56,75 | D11: 55,07 | E11: 56,91 | F11: 53,53 | G11: 55,46 | H11: 56,52 | I11: 58,94 | J11: 60,84 | K11: 61,73 | L11: 61,55 | M11: 56,77 | N11: 58,96 | O11: 65,17 | P11: 64,22 | Q11: 62,08 | R11: 60,44 | S11: 59,93 | T11: 60,16 | U11: 58,11 | V11: 54,29 | W11: 57,31 | X11: 70,08 | Y11: 83,54
A12: SG&A to Sales | B12: 26,11 | C12: 28,70 | D12: 29,12 | E12: 26,40 | F12: 31,02 | G12: 33,48 | H12: 33,50 | I12: 32,78 | J12: 35,01 | K12: 37,32 | L12: 36,17 | M12: 33,34 | N12: 32,70 | O12: 32,95 | P12: 29,27 | Q12: 27,84 | R12: 30,02 | S12: 29,29 | T12: 26,30 | U12: 23,42 | V12: 27,56 | W12: 33,95 | X12: 22,73 | Y12: 56,52
A13: Operating Margin | B13: 32,07 | C13: 28,05 | D13: 25,95 | E13: 30,51 | F13: 22,51 | G13: 21,98 | H13: 23,02 | I13: 26,17 | J13: 25,83 | K13: 24,41 | L13: 25,37 | M13: 23,43 | N13: 26,26 | O13: 32,22 | P13: 34,95 | Q13: 34,24 | R13: 30,43 | S13: 30,64 | T13: 33,86 | U13: 33,22 | V13: 26,73 | W13: 23,36 | X13: 42,43 | Y13: 12,69
A14: Pretax Margin | B14: 34,25 | C14: 27,91 | D14: 25,39 | E14: 35,24 | F14: 26,37 | G14: 24,55 | H14: 25,49 | I14: 24,49 | J14: 26,91 | K14: 26,70 | L14: 26,22 | M14: 24,27 | N14: 26,79 | O14: 32,56 | P14: 37,08 | Q14: 35,93 | R14: 26,86 | S14: 34,19 | T14: 37,82 | U14: 34,89 | V14: 20,39 | W14: 23,65 | X14: 42,07 | Y14: 11,65
A15: Net Margin | B15: 28,62 | C15: 24,03 | D15: 21,35 | E15: 29,53 | F15: 22,08 | G15: 21,28 | H15: 22,44 | I15: 11,40 | J15: 21,71 | K15: 21,51 | L15: 20,69 | M15: 20,45 | N15: 21,59 | O15: 25,72 | P15: 29,21 | Q15: 27,95 | R15: 19,39 | S15: 25,33 | T15: 29,02 | U15: 23,87 | V15: 12,51 | W15: 7,21 | X15: 22,67 | Y15: 8,08
A16: Free Cash Flow Margin | B16: 20,80 | C16: 22,63 | D16: 21,37 | E16: 26,03 | F16: 23,49 | G16: 19,19 | H16: 16,67 | I16: 21,53 | J16: 28,78 | K16: 22,59 | L16: 17,34 | M16: 18,92 | N16: 26,71 | O16: 29,39 | P16: 24,26 | Q16: 36,47 | R16: 25,21 | S16: 20,32 | T16: 15,82 | U16: 26,41 | V16: 20,63 | W16: 14,91 | X16: 26,86 | Y16: 20,86
A17: Capex To Sales | B17: 15,02 | C17: 10,50 | D17: 11,21 | E17: 9,57 | F17: 12,22 | G17: 14,59 | H17: 18,36 | I17: 11,87 | J17: 11,38 | K17: 13,52 | L17: 16,65 | M17: 12,32 | N17: 6,55 | O17: 9,08 | P17: 13,80 | Q17: 3,47 | R17: 10,82 | S17: 14,48 | T17: 17,94 | U17: 13,65 | V17: 11,16 | W17: 12,06 | X17: 8,46 | Y17: 15,11
A18: Return on Assets | B18: 23,48 | C18: 19,23 | D18: 16,55 | E18: 22,40 | F18: 13,52 | G18: 13,50 | H18: 14,29 | I18: 6,94 | J18: 12,37 | K18: 11,44 | L18: 11,34 | M18: 11,93 | N18: 12,97 | O18: 14,93 | P18: 17,30 | Q18: 18,05 | R18: 14,80 | S18: 19,19 | T18: 21,41 | U18: 21,59 | V18: 19,08 | W18: 17,97 | X18: 52,58
A19: Return on Equity | B19: 32,91 | C19: 27,36 | D19: 23,62 | E19: 32,07 | F19: 19,00 | G19: 18,12 | H19: 18,62 | I19: 8,69 | J19: 15,02 | K19: 14,12 | L19: 14,25 | M19: 15,36 | N19: 16,61 | O19: 18,66 | P19: 20,68 | Q19: 20,30 | R19: 16,60 | S19: 21,16 | T19: 23,26 | U19: 23,73 | V19: 22,57 | W19: 26,44 | X19: 82,27
A20: Return on Common Equity | B20: 32,91 | C20: 27,36 | D20: 23,62 | E20: 32,07 | F20: 19,00 | G20: 18,12 | H20: 18,62 | I20: 8,69 | J20: 15,02 | K20: 14,12 | L20: 14,25 | M20: 15,36 | N20: 16,61 | O20: 18,66 | P20: 20,68 | Q20: 20,30 | R20: 16,60 | S20: 21,16 | T20: 23,26 | U20: 23,73 | V20: 22,95 | W20: 28,52 | X20: 82,27
A21: Return on Total Capital | B21: 33,66 | C21: 28,74 | D21: 25,74 | E21: 29,62 | F21: 17,55 | G21: 17,78 | H21: 18,65 | I21: 19,40 | J21: 17,26 | K21: 15,31 | L21: 16,57 | M21: 16,48 | N21: 18,79 | O21: 21,77 | P21: 23,75 | Q21: 24,87 | R21: 26,04 | S21: 25,60 | T21: 27,14 | U21: 33,02 | V21: 48,10 | W21: 83,88
A22: Return on Invested Capital | B22: 30,42 | C22: 24,91 | D22: 21,37 | E22: 28,94 | F22: 17,36 | G22: 17,26 | H22: 18,18 | I22: 8,46 | J22: 14,68 | K22: 13,80 | L22: 13,85 | M22: 14,87 | N22: 15,88 | O22: 18,14 | P22: 20,68 | Q22: 20,30 | R22: 16,60 | S22: 21,16 | T22: 23,26 | U22: 23,73 | V22: 22,56 | W22: 26,16
A23: Cash Flow Return on Invested Capital | B23: 38,07 | C23: 34,35 | D23: 32,61 | E23: 34,88 | F23: 28,08 | G23: 27,41 | H23: 28,38 | I23: 24,77 | J23: 27,17 | K23: 23,17 | L23: 22,76 | M23: 22,72 | N23: 24,47 | O23: 27,13 | P23: 26,95 | Q23: 29,00 | R23: 30,84 | S23: 29,07 | T23: 27,06 | U23: 39,84 | V23: 55,23 | W23: 97,94
A24: Valuation
A25: Price/Sales | B25: 6,74 | C25: 5,79 | D25: 4,13 | E25: 7,62 | F25: 6,60 | G25: 5,80 | H25: 5,37 | I25: 6,68 | J25: 6,17 | K25: 7,33 | L25: 5,54 | M25: 6,36 | N25: 4,71 | O25: 5,58 | P25: 6,59 | Q25: 8,49 | R25: 4,48 | S25: 13,18 | T25: 13,44 | U25: 19,73 | V25: 16,49
A26: Price/Earnings | B26: 23,53 | C26: 24,08 | D26: 19,36 | E26: 25,82 | F26: 29,90 | G26: 27,24 | H26: 23,91 | I26: 58,54 | J26: 28,43 | K26: 34,06 | L26: 27,22 | M26: 31,22 | N26: 21,89 | O26: 21,70 | P26: 22,58 | Q26: 30,38 | R26: 23,11 | S26: 52,03 | T26: 46,33 | U26: 82,66 | V26: 132,18
A27: Price/Book Value | B27: 7,11 | C27: 6,14 | D27: 4,43 | E27: 7,62 | F27: 5,32 | G27: 4,58 | H27: 4,09 | I27: 4,80 | J27: 3,94 | K27: 4,44 | L27: 3,48 | M27: 4,31 | N27: 3,25 | O27: 3,61 | P27: 4,13 | Q27: 5,47 | R27: 3,43 | S27: 9,54 | T27: 8,35 | U27: 12,89 | V27: 18,07
A28: Price/Tangible Book Value | B28: 7,88 | C28: 6,85 | D28: 5,04 | E28: 8,44 | F28: 5,92 | G28: 5,16 | H28: 4,61 | I28: 5,50 | J28: 4,59 | K28: 5,31 | L28: 4,31 | M28: 5,40 | N28: 4,35 | O28: 4,26 | P28: 4,90 | Q28: 6,50 | R28: 4,33 | S28: 10,85 | T28: 9,39 | U28: 13,28 | V28: 19,35
A29: Price/Cash Flow | B29: 18,80 | C29: 17,47 | D29: 12,69 | E29: 21,42 | F29: 18,49 | G29: 17,16 | H29: 15,32 | I29: 19,98 | J29: 15,36 | K29: 20,29 | L29: 16,29 | M29: 20,35 | N29: 14,14 | O29: 14,51 | P29: 17,33 | Q29: 21,26 | R29: 12,44 | S29: 37,86 | T29: 39,81 | U29: 49,23 | V29: 53,83
A30: Price/Free Cash Flow | B30: 32,38 | C30: 25,57 | D30: 19,35 | E30: 29,30 | F30: 28,11 | G30: 30,21 | H30: 32,19 | I30: 31,00 | J30: 21,44 | K30: 32,43 | L30: 31,93 | M30: 33,60 | N30: 17,61 | O30: 18,99 | P30: 27,18 | Q30: 23,28 | R30: 17,78 | S30: 64,83 | T30: 84,96 | U30: 74,69 | V30: 79,92
A31: Dividend Yield (%) | B31: 0,32 | C31: 0,00 | D31: 0,00 | E31: 0,00 | F31: 0,00 | G31: 0,00 | H31: 0,00 | I31: 0,00 | J31: 0,00 | K31: 0,00 | L31: 0,00 | M31: 0,00 | N31: 0,00 | O31: 0,00 | P31: 0,00 | Q31: 0,00 | R31: 0,00 | S31: 0,00 | T31: 0,00 | U31: 0,00 | V31: 0,00
A32: Enterprise Value/EBIT | B32: 20,00 | C32: 19,26 | D32: 14,41 | E32: 23,00 | F32: 26,18 | G32: 23,07 | H32: 19,72 | I32: 21,82 | J32: 20,08 | K32: 26,00 | L32: 18,07 | M32: 23,07 | N32: 14,55 | O32: 13,89 | P32: 15,65 | Q32: 21,60 | R32: 12,23 | S32: 39,76 | T32: 36,49 | U32: 55,60 | V32: 59,57
A33: Enterprise Value/EBITDA | B33: 17,60 | C33: 16,92 | D33: 11,82 | E33: 19,86 | F33: 19,63 | G33: 17,32 | H33: 15,33 | I33: 17,63 | J33: 15,87 | K33: 20,28 | L33: 14,16 | M33: 18,01 | N33: 11,87 | O33: 12,06 | P33: 13,77 | Q33: 18,14 | R33: 9,97 | S33: 33,40 | T33: 31,48 | U33: 48,60 | V33: 50,73
A34: Enterprise Value/Sales | B34: 6,42 | C34: 5,40 | D34: 3,74 | E34: 7,02 | F34: 5,89 | G34: 5,07 | H34: 4,54 | I34: 5,71 | J34: 5,19 | K34: 6,34 | L34: 4,58 | M34: 5,41 | N34: 3,82 | O34: 4,47 | P34: 5,47 | Q34: 7,40 | R34: 3,72 | S34: 12,18 | T34: 12,36 | U34: 18,47 | V34: 15,92
A35: Total Debt/Enterprise Value | B35: 0,01 | C35: 0,02 | D35: 0,03 | E35: 0,02 | F35: 0,03 | G35: 0,02 | H35: 0,01 | I35: 0,01 | J35: 0,01 | K35: 0,01 | L35: 0,02 | M35: 0,02 | N35: 0,03 | O35: 0,02 | P35: 0,02 | Q35: 0,00 | R35: 0,00 | S35: 0,00 | T35: 0,00 | U35: 0,00 | V35: 0,00
A36: Per Share
A37: Sales per Share | B37: 28,10 | C37: 24,14 | D37: 21,34 | E37: 19,00 | F37: 13,27 | G37: 11,55 | H37: 9,74 | I37: 7,89 | J37: 6,42 | K37: 5,31 | L37: 4,79 | M37: 4,41 | N37: 3,76 | O37: 2,90 | P37: 2,25 | Q37: 1,83 | R37: 1,72 | S37: 1,31 | T37: 0,86 | U37: 0,53 | V37: 0,29 | W37: 0,13 | X37: 0,05 | Y37: 0,01
A38: EBIT (Operating Income) per Share | B38: 9,01 | C38: 6,77 | D38: 5,54 | E38: 5,80 | F38: 2,99 | G38: 2,54 | H38: 2,24 | I38: 2,06 | J38: 1,66 | K38: 1,30 | L38: 1,22 | M38: 1,03 | N38: 0,99 | O38: 0,93 | P38: 0,79 | Q38: 0,63 | R38: 0,52 | S38: 0,40 | T38: 0,29 | U38: 0,17 | V38: 0,08 | W38: 0,03 | X38: 0,02 | Y38: 0,00
A39: EPS (recurring) | B39: 7,81 | C39: 5,92 | D39: 4,73 | E39: 5,07 | F39: 2,67 | G39: 2,40 | H39: 2,23 | I39: 1,04 | J39: 1,41 | K39: 1,16 | L39: 1,00 | M39: 0,90 | N39: 0,87 | O39: 0,79 | P39: 0,68 | Q39: 0,52 | R39: 0,39 | S39: 0,33 | T39: 0,32 | U39: 0,13 | V39: 0,05 | W39: 0,01 | X39: 0,01 | Y39: 0,00
A40: EPS (basic) | B40: 8,13 | C40: 5,84 | D40: 4,59 | E40: 5,69 | F40: 2,96 | G40: 2,48 | H40: 2,21 | I40: 0,91 | J40: 1,42 | K40: 1,16 | L40: 0,99 | M40: 0,91 | N40: 0,82 | O40: 0,76 | P40: 0,67 | Q40: 0,52 | R40: 0,34 | S40: 0,34 | T40: 0,26 | U40: 0,13 | V40: 0,05 | W40: 0,01 | X40: 0,01 | Y40: 0,00
A41: EPS (diluted) | B41: 8,04 | C41: 5,80 | D41: 4,56 | E41: 5,61 | F41: 2,93 | G41: 2,46 | H41: 2,19 | I41: 0,90 | J41: 1,39 | K41: 1,14 | L41: 0,97 | M41: 0,90 | N41: 0,81 | O41: 0,74 | P41: 0,66 | Q41: 0,51 | R41: 0,33 | S41: 0,33 | T41: 0,25 | U41: 0,13 | V41: 0,04 | W41: 0,01 | X41: 0,01 | Y41: 0,00
A42: Dividends per Share | B42: 0,60 | C42: 0,00 | D42: 0,00 | E42: 0,00 | F42: 0,00 | G42: 0,00 | H42: 0,00 | I42: 0,00 | J42: 0,00 | K42: 0,00 | L42: 0,00 | M42: 0,00 | N42: 0,00 | O42: 0,00 | P42: 0,00 | Q42: 0,00 | R42: 0,00 | S42: 0,00 | T42: 0,00 | U42: 0,00 | V42: 0,00
A43: Dividend Payout Ratio (%) | B43: 7,46 | C43: 0,00 | D43: 0,00 | E43: 0,00 | F43: 0,00 | G43: 0,00 | H43: 0,00 | I43: 0,00 | J43: 0,00 | K43: 0,00 | L43: 0,00 | M43: 0,00 | N43: 0,00 | O43: 0,00 | P43: 0,00 | Q43: 0,00 | R43: 0,00 | S43: 0,00 | T43: 0,00 | U43: 0,00 | V43: 0,00
A44: Book Value per Share | B44: 26,62 | C44: 22,74 | D44: 19,93 | E44: 19,00 | F44: 16,48 | G44: 14,63 | H44: 12,77 | I44: 10,97 | J44: 10,06 | K44: 8,75 | L44: 7,63 | M44: 6,51 | N44: 5,44 | O44: 4,48 | P44: 3,60 | Q44: 2,84 | R44: 2,24 | S44: 1,81 | T44: 1,38 | U44: 0,81 | V44: 0,27 | W44: 0,05 | X44: 0,02
A45: Tangible Book Value per Share | B45: 24,01 | C45: 20,40 | D45: 17,52 | E45: 17,16 | F45: 14,80 | G45: 12,99 | H45: 11,32 | I45: 9,58 | J45: 8,63 | K45: 7,32 | L45: 6,15 | M45: 5,20 | N45: 4,07 | O45: 3,79 | P45: 3,03 | Q45: 2,39 | R45: 1,78 | S45: 1,59 | T45: 1,23 | U45: 0,78 | V45: 0,25 | W45: 0,04 | X45: 0,02
A46: Cash Flow per Share | B46: 10,07 | C46: 8,00 | D46: 6,95 | E46: 6,76 | F46: 4,74 | G46: 3,90 | H46: 3,41 | I46: 2,64 | J46: 2,58 | K46: 1,92 | L46: 1,63 | M46: 1,38 | N46: 1,25 | O46: 1,11 | P46: 0,86 | Q46: 0,73 | R46: 0,62 | S46: 0,46 | T46: 0,29 | U46: 0,21 | V46: 0,09 | W46: 0,04 | X46: 0,02 | Y46: 0,00
A47: Free Cash Flow per Share | B47: 5,85 | C47: 5,46 | D47: 4,56 | E47: 4,94 | F47: 3,12 | G47: 2,22 | H47: 1,62 | I47: 1,70 | J47: 1,85 | K47: 1,20 | L47: 0,83 | M47: 0,83 | N47: 1,01 | O47: 0,85 | P47: 0,55 | Q47: 0,67 | R47: 0,43 | S47: 0,27 | T47: 0,14 | U47: 0,14 | V47: 0,06 | W47: 0,02 | X47: 0,01 | Y47: 0,00
A48: Diluted Shares Outstanding (M) (M) | B48: 12.447,00 | C48: 12.722,00 | D48: 13.159,00 | E48: 13.553,48 | F48: 13.740,56 | G48: 13.971,12 | H48: 14.065,70 | I48: 14.071,68 | J48: 13.974,12 | K48: 13.858,60 | L48: 13.741,40 | M48: 13.539,25 | N48: 13.279,35 | O48: 13.075,90 | P48: 12.917,54 | Q48: 12.764,28 | R48: 12.688,28 | S48: 12.636,17 | T48: 12.369,95 | U48: 11.663,67 | V48: 10.900,69 | W48: 10.926,06 | X48: 9.755,00 | Y48: 7.463,82
A49: Basic Shares Outstanding (M) (M) | B49: 12.319,00 | C49: 12.630,00 | D49: 13.063,00 | E49: 13.353,00 | F49: 13.616,32 | G49: 13.851,92 | H49: 13.902,80 | I49: 13.858,02 | J49: 13.755,56 | K49: 13.692,52 | L49: 13.518,70 | M49: 13.300,97 | N49: 13.075,86 | O49: 12.898,63 | P49: 12.735,75 | Q49: 12.636,61 | R49: 12.546,22 | S49: 12.420,22 | T49: 12.044,46 | U49: 11.023,09 | V49: 7.719,57 | W49: 10.926,06 | X49: 9.755,00 | Y49: 3.777,26
A50: Total Shares Outstanding (M) (M) | B50: 12.211,00 | C50: 12.460,00 | D50: 12.849,00 | E50: 13.242,42 | F50: 13.504,44 | G50: 13.766,70 | H50: 13.911,12 | I50: 13.895,66 | J50: 13.825,86 | K50: 13.746,96 | L50: 13.603,44 | M50: 13.420,30 | N50: 13.186,40 | O50: 12.983,22 | P50: 12.839,61 | Q50: 12.698,59 | R50: 12.592,37 | S50: 12.504,58 | T50: 12.347,95 | U50: 11.696,21 | V50: 10.970,26 | W50: 10.926,06 | X50: 9.755,00
A51: Asset Turnover Analysis
A52: Cash & ST Investments | B52: 3,39 | C52: 2,73 | D52: 2,22 | E52: 1,86 | F52: 1,42 | G52: 1,41 | H52: 1,30 | I52: 1,18 | J52: 1,13 | K52: 1,07 | L52: 1,07 | M52: 1,12 | N52: 1,08 | O52: 0,95 | P52: 0,98 | Q52: 1,16 | R52: 1,45 | S52: 1,30 | T52: 1,10 | U52: 1,21 | V52: 2,57 | W52: 6,09 | X52: 4,89
A53: Receivables | B53: 6,97 | C53: 6,96 | D53: 6,98 | E53: 7,19 | F53: 6,19 | G53: 6,63 | H53: 6,87 | I53: 6,74 | J53: 6,38 | K53: 5,94 | L53: 6,51 | M53: 6,65 | N53: 6,77 | O53: 6,78 | P53: 7,10 | Q53: 7,98 | R53: 8,81 | S53: 9,14 | T53: 10,55 | U53: 11,47 | V53: 11,88 | W53: 13,53
A54: Inventories | C54: 99,52 | D54: 65,73 | E54: 116,90 | F54: 98,13 | G54: 68,28 | H54: 64,17 | I54: 89,64 | J54: 92,59 | K54: 114,72 | L54: 118,84 | M54: 55,48 | N54: 81,21
A55: Current Assets | B55: 2,09 | C55: 1,83 | D55: 1,59 | E55: 1,42 | F55: 1,12 | G55: 1,12 | H55: 1,05 | I55: 0,97 | J55: 0,92 | K55: 0,87 | L55: 0,87 | M55: 0,90 | N55: 0,88 | O55: 0,80 | P55: 0,82 | Q55: 0,95 | R55: 1,16 | S55: 1,09 | T55: 0,96 | U55: 1,05 | V55: 1,96 | W55: 3,70 | X55: 3,31
A56: Fixed Assets | B56: 2,10 | C56: 2,23 | D56: 2,36 | E56: 2,48 | F56: 2,01 | G56: 2,24 | H56: 2,68 | I56: 2,90 | J56: 2,84 | K56: 2,78 | L56: 3,26 | M56: 4,21 | N56: 4,66 | O56: 4,36 | P56: 4,62 | Q56: 4,63 | R56: 4,70 | S56: 5,16 | T56: 6,32 | U56: 9,16 | V56: 11,25 | W56: 12,11
A57: Total Assets | B57: 0,82 | C57: 0,80 | D57: 0,78 | E57: 0,76 | F57: 0,61 | G57: 0,63 | H57: 0,64 | I57: 0,61 | J57: 0,57 | K57: 0,53 | L57: 0,55 | M57: 0,58 | N57: 0,60 | O57: 0,58 | P57: 0,59 | Q57: 0,65 | R57: 0,76 | S57: 0,76 | T57: 0,74 | U57: 0,90 | V57: 1,52 | W57: 2,49 | X57: 2,32
A58: DuPont Analysis
A59: Asset Turnover (x) | B59: 0,82 | C59: 0,80 | D59: 0,78 | E59: 0,76 | F59: 0,61 | G59: 0,63 | H59: 0,64 | I59: 0,61 | J59: 0,57 | K59: 0,53 | L59: 0,55 | M59: 0,58 | N59: 0,60 | O59: 0,58 | P59: 0,59 | Q59: 0,65 | R59: 0,76 | S59: 0,76 | T59: 0,74 | U59: 0,90 | V59: 1,52 | W59: 2,49 | X59: 2,32
A60: x Pretax Margin (%) | B60: 34,25 | C60: 27,91 | D60: 25,39 | E60: 35,24 | F60: 26,37 | G60: 24,55 | H60: 25,49 | I60: 24,49 | J60: 26,91 | K60: 26,70 | L60: 26,22 | M60: 24,27 | N60: 26,79 | O60: 32,56 | P60: 37,08 | Q60: 35,93 | R60: 26,86 | S60: 34,19 | T60: 37,82 | U60: 34,89 | V60: 20,39 | W60: 23,65 | X60: 42,07 | Y60: 11,65
A61: =Pretax Return on Assets(%) -> #ERROR! | B61: 28,10 | C61: 22,33 | D61: 19,69 | E61: 26,73 | F61: 16,15 | G61: 15,58 | H61: 16,24 | I61: 14,91 | J61: 15,34 | K61: 14,21 | L61: 14,38 | M61: 14,16 | N61: 16,09 | O61: 18,90 | P61: 21,95 | Q61: 23,20 | R61: 20,50 | S61: 25,90 | T61: 27,91 | U61: 31,56 | V61: 31,09 | W61: 58,95 | X61: 97,56
A62: x Tax Rate Complement (1-Tax Rate) (%) | B62: 83,56 | C62: 86,09 | D62: 84,08 | E62: 83,80 | F62: 83,75 | G62: 86,67 | H62: 88,04 | I62: 46,56 | J62: 80,65 | K62: 83,19 | L62: 78,92 | M62: 84,26 | N62: 80,59 | O62: 79,00 | P62: 78,78 | Q62: 77,80 | R62: 72,21 | S62: 74,09 | T62: 76,72 | U62: 68,42 | V62: 61,38 | W62: 30,48 | X62: 53,89 | Y62: 69,38
A63: =Return on Assets(%) -> #ERROR! | B63: 23,48 | C63: 19,23 | D63: 16,55 | E63: 22,40 | F63: 13,52 | G63: 13,50 | H63: 14,29 | I63: 6,94 | J63: 12,37 | K63: 11,44 | L63: 11,34 | M63: 11,93 | N63: 12,97 | O63: 14,93 | P63: 17,30 | Q63: 18,05 | R63: 14,80 | S63: 19,19 | T63: 21,41 | U63: 21,59 | V63: 19,08 | W63: 17,97 | X63: 52,58
A64: x Equity Multiplier (Assets/Equity) | B64: 1,40 | C64: 1,42 | D64: 1,43 | E64: 1,43 | F64: 1,40 | G64: 1,34 | H64: 1,30 | I64: 1,25 | J64: 1,21 | K64: 1,23 | L64: 1,26 | M64: 1,29 | N64: 1,28 | O64: 1,25 | P64: 1,20 | Q64: 1,12 | R64: 1,12 | S64: 1,10 | T64: 1,09 | U64: 1,10 | V64: 1,18 | W64: 1,47 | X64: 1,56
A65: =Return on Equity(%) -> #ERROR! | B65: 32,91 | C65: 27,36 | D65: 23,62 | E65: 32,07 | F65: 19,00 | G65: 18,12 | H65: 18,62 | I65: 8,69 | J65: 15,02 | K65: 14,12 | L65: 14,25 | M65: 15,36 | N65: 16,61 | O65: 18,66 | P65: 20,68 | Q65: 20,30 | R65: 16,60 | S65: 21,16 | T65: 23,26 | U65: 23,73 | V65: 22,57 | W65: 26,44 | X65: 82,27
A66: x Earnings Retention (1-Payout) (%) | B66: 92,54 | C66: 100,00 | D66: 100,00 | E66: 100,00 | F66: 100,00 | G66: 100,00 | H66: 100,00 | I66: 100,00 | J66: 100,00 | K66: 100,00 | L66: 100,00 | M66: 100,00 | N66: 100,00 | O66: 100,00 | P66: 100,00 | Q66: 100,00 | R66: 100,00 | S66: 100,00 | T66: 100,00 | U66: 100,00 | V66: 100,00
A67: =Reinvestment Rate(%) -> #ERROR! | B67: 30,49 | C67: 27,36 | D67: 23,62 | E67: 32,07 | F67: 19,00 | G67: 18,12 | H67: 18,62 | I67: 8,69 | J67: 15,02 | K67: 14,12 | L67: 14,25 | M67: 15,36 | N67: 16,61 | O67: 18,66 | P67: 20,68 | Q67: 20,30 | R67: 16,60 | S67: 21,16 | T67: 23,26 | U67: 23,73 | V67: 22,57 | W67: 26,44 | X67: 82,27
A68: Note: EBIT Return on Assets (%) | B68: 26,31 | C68: 22,44 | D68: 20,12 | E68: 23,15 | F68: 13,79 | G68: 13,95 | H68: 14,66 | I68: 15,93 | J68: 14,72 | K68: 12,98 | L68: 13,91 | M68: 13,67 | N68: 15,77 | O68: 18,71 | P68: 20,70 | Q68: 22,11 | R68: 23,23 | S68: 23,21 | T68: 24,98 | U68: 30,05 | V68: 40,76 | W68: 58,23 | X68: 98,38
A69: Note: Interest as % Assets | B69: 0,06 | C69: 0,08 | D69: 0,10 | E69: 0,10 | F69: 0,04 | G69: 0,04 | H69: 0,05 | I69: 0,06 | J69: 0,07 | K69: 0,07 | L69: 0,08 | M69: 0,07 | N69: 0,09 | O69: 0,08 | P69: 0,00 | Q69: 0,00 | R69: 0,00 | S69: 0,00 | T69: 0,00 | U69: 0,01 | V69: 0,03 | W69: 0,22 | X69: 0,87 | Y69: 2,08
A70: Operating Efficiency
A71: Revenue/Employee (actual) | B71: 1.908.146 | C71: 1.683.034 | D71: 1.476.471 | E71: 1.645.291 | F71: 1.347.736 | G71: 1.357.471 | H71: 1.386.622 | I71: 1.385.894 | J71: 1.245.375 | K71: 1.190.507 | L71: 1.228.172 | M71: 1.250.733 | N71: 927.536 | O71: 1.166.169 | P71: 1.193.361 | Q71: 1.175.995 | R71: 1.077.814 | S71: 987.443 | T71: 993.528 | U71: 1.080.732 | V71: 1.055.685 | W71: 900.451 | X71: 644.44 | Y71: 304.317
A72: Net Income/Employee (actual) | B72: 546.129 | C72: 404.352 | D72: 315.254 | E72: 485.834 | F72: 297.625 | G72: 288.842 | H72: 311.184 | I72: 158.058 | J72: 270.329 | K72: 256.026 | L72: 254.104 | M72: 255.758 | N72: 200.293 | O72: 299.905 | P72: 348.566 | Q72: 328.734 | R72: 209.023 | S72: 250.147 | T72: 288.312 | U72: 257.992 | V72: 132.115 | W72: 64.894 | X72: 146.123 | Y72: 24.595
A73: Assets/Employee (actual) | B73: 2.456.080 | C73: 2.204.864 | D73: 1.920.077 | E73: 2.295.642 | F73: 2.362.259 | G73: 2.320.533 | H73: 2.356.886 | I73: 2.462.801 | J73: 2.324.636 | K73: 2.385.560 | L73: 2.410.205 | M73: 2.322.640 | N73: 1.741.483 | O73: 2.235.316 | P73: 2.370.943 | Q73: 2.041.683 | R73: 1.570.941 | S73: 1.507.635 | T73: 1.730.687 | U73: 1.808.418 | V73: 1.092.936 | W73: 541.475 | X73: 432.004 | Y73: 297.384
A74: Receivables Turnover | B74: 6,97 | C74: 6,96 | D74: 6,98 | E74: 7,19 | F74: 6,19 | G74: 6,63 | H74: 6,87 | I74: 6,74 | J74: 6,38 | K74: 5,94 | L74: 6,51 | M74: 6,65 | N74: 6,77 | O74: 6,78 | P74: 7,10 | Q74: 7,98 | R74: 8,81 | S74: 9,14 | T74: 10,55 | U74: 11,47 | V74: 11,88 | W74: 13,53
A75: Inventory Turnover | C75: 99,52 | D75: 65,73 | E75: 116,90 | F75: 98,13 | G75: 68,28 | H75: 64,17 | I75: 89,64 | J75: 92,59 | K75: 114,72 | L75: 118,84 | M75: 55,48 | N75: 81,21
A76: Payables Turnover | B76: 18,90 | C76: 20,63 | D76: 22,88 | E76: 19,16 | F76: 15,15 | G76: 14,45 | H76: 15,94 | I76: 17,79 | J76: 17,58 | K76: 15,72 | L76: 11,94 | M76: 11,53 | N76: 16,16 | O76: 24,63 | P76: 29,81 | Q76: 44,91 | R76: 37,48 | S76: 26,96 | T76: 25,86 | U76: 34,69 | V76: 36,97 | W76: 22,53
A77: Asset Turnover | B77: 0,82 | C77: 0,80 | D77: 0,78 | E77: 0,76 | F77: 0,61 | G77: 0,63 | H77: 0,64 | I77: 0,61 | J77: 0,57 | K77: 0,53 | L77: 0,55 | M77: 0,58 | N77: 0,60 | O77: 0,58 | P77: 0,59 | Q77: 0,65 | R77: 0,76 | S77: 0,76 | T77: 0,74 | U77: 0,90 | V77: 1,52 | W77: 2,49 | X77: 2,32
A78: Working Capital Turnover | B78: 4,69 | C78: 3,42 | D78: 2,94 | E78: 2,08 | F78: 1,55 | G78: 1,50 | H78: 1,36 | I78: 1,11 | J78: 1,01 | K78: 1,04 | L78: 1,06 | M78: 1,05 | N78: 1,08 | O78: 0,86 | P78: 0,92 | Q78: 0,88 | R78: 1,22 | S78: 1,09 | T78: 0,90 | U78: 0,74 | V78: 1,36 | W78: 4,51 | X78: 3,09 | Y78: 11,79
A79: Operating Cycle - Days
A80: Days of Inventory on Hand | C80: 3,67 | D80: 5,55 | E80: 3,12 | F80: 3,72 | G80: 5,35 | H80: 5,69 | I80: 4,07 | J80: 3,94 | K80: 3,18 | L80: 3,07 | M80: 6,58 | N80: 4,49
A81: =+ Days of Sales Outstanding -> #ERROR! | B81: 52,33 | C81: 52,42 | D81: 52,32 | E81: 50,79 | F81: 58,92 | G81: 55,05 | H81: 53,17 | I81: 54,14 | J81: 57,23 | K81: 61,40 | L81: 56,11 | M81: 54,92 | N81: 53,91 | O81: 53,86 | P81: 51,42 | Q81: 45,72 | R81: 41,45 | S81: 39,92 | T81: 34,60 | U81: 31,82 | V81: 30,73 | W81: 26,98
A82: =Operating Cycle -> #ERROR! | C82: 56,09 | D82: 57,88 | E82: 53,91 | F82: 62,64 | G82: 60,39 | H82: 58,85 | I82: 58,21 | J82: 61,18 | K82: 64,58 | L82: 59,18 | M82: 61,50 | N82: 58,40
A83: - Days of Payables Outstanding | B83: 19,31 | C83: 17,69 | D83: 15,96 | E83: 19,05 | F83: 24,09 | G83: 25,27 | H83: 22,89 | I83: 20,51 | J83: 20,76 | K83: 23,22 | L83: 30,56 | M83: 31,65 | N83: 22,58 | O83: 14,82 | P83: 12,24 | Q83: 8,13 | R83: 9,74 | S83: 13,54 | T83: 14,11 | U83: 10,52 | V83: 9,87 | W83: 16,20
A84: =Net Operating Cycle -> #ERROR! | C84: 38,39 | D84: 41,92 | E84: 34,86 | F84: 38,55 | G84: 35,13 | H84: 35,96 | I84: 37,70 | J84: 40,41 | K84: 41,36 | L84: 28,62 | M84: 29,85 | N84: 35,82
A85: Liquidity
A86: Current Ratio (x) | B86: 1,84 | C86: 2,10 | D86: 2,38 | E86: 2,93 | F86: 3,07 | G86: 3,37 | H86: 3,92 | I86: 5,14 | J86: 6,29 | K86: 4,67 | L86: 4,69 | M86: 4,58 | N86: 4,22 | O86: 5,92 | P86: 4,16 | Q86: 10,62 | R86: 8,77 | S86: 8,49 | T86: 10,00 | U86: 12,08 | V86: 7,91 | W86: 2,38 | X86: 2,59 | Y86: 1,28
A87: Quick Ratio (x) | B87: 1,84 | C87: 2,10 | D87: 2,34 | E87: 2,91 | F87: 3,05 | G87: 3,35 | H87: 3,89 | I87: 5,11 | J87: 6,27 | K87: 4,64 | L87: 4,69 | M87: 4,55 | N87: 4,18 | O87: 5,92 | P87: 4,16 | Q87: 10,62 | R87: 8,77 | S87: 8,49 | T87: 10,00 | U87: 12,08 | V87: 7,91 | W87: 2,38 | X87: 2,59
A88: Cash Ratio | B88: 1,07 | C88: 1,36 | D88: 1,64 | E88: 2,17 | F88: 2,41 | G88: 2,65 | H88: 3,15 | I88: 4,21 | J88: 5,15 | K88: 3,78 | L88: 3,84 | M88: 3,69 | N88: 3,35 | O88: 5,01 | P88: 3,50 | Q88: 8,91 | R88: 6,88 | S88: 6,98 | T88: 8,62 | U88: 10,78 | V88: 6,30 | W88: 1,42 | X88: 1,63 | Y88: 1,28
A89: Cash & ST Inv/Current Assets | B89: 58,43 | C89: 64,66 | D89: 69,03 | E89: 74,22 | F89: 78,43 | G89: 78,44 | H89: 80,44 | I89: 81,95 | J89: 81,90 | K89: 81,08 | L89: 81,87 | M89: 80,56 | N89: 79,54 | O89: 84,59 | P89: 84,15 | Q89: 83,95 | R89: 78,53 | S89: 82,24 | T89: 86,23 | U89: 89,26 | V89: 79,58 | W89: 59,75 | X89: 63,13 | Y89: 100,00
A90: CFO/Current Liabilities | B90: 140,59 | C90: 124,36 | D90: 132,03 | E90: 142,64 | F90: 114,59 | G90: 120,56 | H90: 138,56 | I90: 153,38 | J90: 215,06 | K90: 137,61 | L90: 133,36 | M90: 117,29 | N90: 115,92 | O90: 163,41 | P90: 110,85 | Q90: 339,08 | R90: 341,12 | S90: 283,72 | T90: 274,46 | U90: 329,95 | V90: 287,06 | W90: 167,95 | X90: 173,46 | Y90: 118,38
A91: Coverage
A92: Net Debt/EBITDA | B92: -0,64 | C92: -0,98 | D92: -1,11 | E92: -1,37 | F92: -2,22 | G92: -2,44 | H92: -2,59 | I92: -2,72 | J92: -2,81 | K92: -2,95 | L92: -2,78 | M92: -2,98 | N92: -2,65 | O92: -2,88 | P92: -2,72 | Q92: -2,57 | R92: -1,95 | S92: -2,35 | T92: -2,70 | U92: -3,44 | V92: -2,14 | W92: -0,84 | X92: -0,66
A93: Net Debt/(EBITDA-Capex) | B93: -0,90 | C93: -1,23 | D93: -1,46 | E93: -1,67 | F93: -3,35 | G93: -4,37 | H93: -6,81 | I93: -4,30 | J93: -4,31 | K93: -5,19 | L93: -5,72 | M93: -5,06 | N93: -3,32 | O93: -3,81 | P93: -4,17 | Q93: -2,81 | R93: -2,74 | S93: -3,90 | T93: -4,98 | U93: -5,37 | V93: -3,32 | W93: -1,52 | X93: -0,81
A94: Total Debt/EBITDA | B94: 0,11 | C94: 0,15 | D94: 0,17 | E94: 0,16 | F94: 0,27 | G94: 0,10 | H94: 0,10 | I94: 0,11 | J94: 0,13 | K94: 0,23 | L94: 0,25 | M94: 0,29 | N94: 0,34 | O94: 0,30 | P94: 0,30 | Q94: 0,00 | R94: 0,00 | S94: 0,00 | T94: 0,00 | U94: 0,00 | V94: 0,00 | W94: 0,02 | X94: 0,05
A95: EBIT/Interest Expense (Int. Coverage) | B95: 242,81 | C95: 176,16 | D95: 150,27 | E95: 154,35 | F95: 116,28 | G95: 132,86 | H95: 153,06 | I95: 185,04 | J95: 186,91 | K95: 172,70 | L95: 165,38 | M95: 168,60 | N95: 156,18 | O95: 210,33 | S95: 4.226,43 | T95: 13.971,97 | U95: 2.627,94 | V95: 989,02 | W95: 177,35 | X95: 72,55 | Y95: 6,24
A96: EBITDA/Interest Expense | B96: 475,71 | C96: 318,47 | D96: 248,76 | E96: 263,02 | F96: 405,51 | G96: 472,54 | H96: 355,84 | I96: 329,96 | J96: 236,46 | K96: 221,38 | L96: 210,94 | M96: 216,06 | N96: 191,44 | O96: 242,24 | S96: 5.030,81 | T96: 16.197,43 | U96: 3.006,56 | V96: 1.161,26 | W96: 203,34 | X96: 79,57 | Y96: 11,95
A97: Fixed-charge Coverage Ratio | B97: 242,81 | C97: 176,16 | D97: 150,27 | E97: 154,35 | F97: 116,28 | G97: 132,86 | H97: 153,06 | I97: 185,04 | J97: 186,91 | K97: 172,70 | L97: 165,38 | M97: 168,60 | N97: 156,18 | O97: 210,33 | S97: 4.226,43 | T97: 13.971,97 | U97: 2.627,94 | V97: 989,02 | W97: 177,35 | X97: 72,55 | Y97: 6,24
A98: CFO/Interest Expense | B98: 467,53 | C98: 330,34 | D98: 256,29 | E98: 264,89 | F98: 482,40 | G98: 545,20 | H98: 420,80 | I98: 340,28 | J98: 290,61 | K98: 255,50 | L98: 221,54 | M98: 224,81 | N98: 197,85 | O98: 251,12 | S98: 4.800,84 | T98: 13.931,94 | U98: 3.169,36 | V98: 1.133,46 | W98: 204,79 | X98: 60,41 | Y98: 17,68
A99: Cash Dividend Coverage Ratio | B99: 18,16
A100: LT Debt/EBITDA | B100: 0,19 | C100: 0,26 | D100: 0,31 | E100: 0,29 | F100: 0,46 | G100: 0,31 | H100: 0,10 | I100: 0,11 | J100: 0,13 | K100: 0,09 | L100: 0,15 | M100: 0,12 | N100: 0,19 | O100: 0,21 | P100: 0,00 | Q100: 0,00 | R100: 0,00 | S100: 0,00 | T100: 0,00 | U100: 0,00 | V100: 0,00 | W100: 0,01 | X100: 0,03
A101: Net Debt/FFO | B101: -0,50 | C101: -0,77 | D101: -0,89 | E101: -1,19 | F101: -1,72 | G101: -1,93 | H101: -2,44 | I101: -3,52 | J101: -2,52 | K101: -2,51 | L101: -2,73 | M101: -2,86 | N101: -2,71 | O101: -2,90 | P101: -2,82 | Q101: -2,77 | R101: -2,11 | S101: -2,61 | T101: -3,18 | U101: -3,33 | V101: -1,74 | W101: -0,82 | X101: -0,90
A102: LT Debt/FFO | B102: 0,18 | C102: 0,24 | D102: 0,29 | E102: 0,28 | F102: 0,40 | G102: 0,28 | H102: 0,09 | I102: 0,14 | J102: 0,12 | K102: 0,07 | L102: 0,15 | M102: 0,12 | N102: 0,19 | O102: 0,21 | P102: 0,00 | Q102: 0,00 | R102: 0,00 | S102: 0,00 | T102: 0,00 | U102: 0,00 | V102: 0,00 | W102: 0,00 | X102: 0,04
...

Sheet M&A Deals
A1: Alphabet Inc. Class C (GOOG) $160.89
A3: All M&A Deals (498)
A4: Announce Date | B4: Close Date | C4: Target | D4: Acquirer | E4: Deal Type | F4: Transaction Value | G4: EV/EBITDA | H4: Role | I4: Target Industry
A5: 18 Mar '25 | B5: Pending | C5: Wiz, Inc. (United States) | D5: Google LLC | E5: Acquisition / Merger | F5: 32000 | G5: - | H5: Buyer | I5: Packaged Software
A6: 06 Feb '25 | B6: 06 Feb '25 | C6: Caraway, Inc. | D6: Summer Health, Inc. | E6: Acquisition / Merger | F6: - | G6: - | H6: Seller | I6: Packaged Software
A7: 22 Jan '25 | B7: Pending | C7: HTC Corp. /XR Business/ | D7: Google LLC | E7: Acquisition / Merger | F7: 250 | G7: - | H7: Buyer | I7: Miscellaneous Commercial Services
A8: 10 Jan '25 | B8: Pending | C8: Machinify, Inc. | D8: New Mountain Capital LLC | E8: Acquisition / Merger | F8: - | G8: - | H8: Seller | I8: Packaged Software
A9: 20 Nov '24 | B9: 20 Nov '24 | C9: Odoo SA | D9: Private Equity Group | E9: Minority Stake | F9: 529.3 | G9: 12.9 | H9: Buyer | I9: Packaged Software
A10: 23 Jul '24 | B10: 23 Jul '24 | C10: Planck Resolution Ltd. | D10: Applied Systems, Inc. | E10: Acquisition / Merger | F10: 300 | G10: - | H10: Buyer | I10: Packaged Software
A11: 14 Jul '24 | B11: Rumor Cancelled | C11: Wiz, Inc. (United States) | D11: Alphabet, Inc. | E11: Acquisition / Merger | F11: 23000 | G11: - | H11: Buyer | I11: Packaged Software
A12: 05 Jun '24 | B12: 05 Jun '24 | C12: Cameyo, Inc. | D12: Google LLC | E12: Acquisition / Merger | F12: - | G12: - | H12: Buyer | I12: Packaged Software
A13: 29 May '24 | B13: 29 May '24 | C13: Lotus Software, Inc. | D13: Chameleon Intelligent Tech, Inc. | E13: Acquisition / Merger | F13: - | G13: - | H13: Seller | I13: Packaged Software
A14: 04 Apr '24 | B14: Rumor Cancelled | C14: HubSpot, Inc. | D14: Alphabet, Inc. | E14: Acquisition / Merger | F14: - | G14: - | H14: Buyer | I14: Packaged Software
A15: 31 Aug '23 | B15: 31 Aug '23 | C15: Fyyne, Inc. | D15: Salescabal, Inc. | E15: Acquisition / Merger | F15: - | G15: - | H15: Seller | I15: Packaged Software
A16: 24 Aug '23 | B16: 24 Aug '23 | C16: Equalum Ltd. | D16: Google LLC | E16: Acquisition / Merger | F16: - | G16: - | H16: Buyer | I16: Data Processing Services
A17: 17 Aug '23 | B17: 31 Mar '24 | C17: TeamSystem Holdco SpA | D17: Private Equity Group | E17: Minority Stake | F17: - | G17: - | H17: Buyer | I17: Packaged Software
A18: 15 Jun '23 | B18: 07 Sep '23 | C18: Google LLC /Domains Business/ | D18: Squarespace, Inc. | E18: Acquisition / Merger | F18: - | G18: - | H18: Seller | I18: Packaged Software
A19: 21 Feb '23 | B19: 28 Mar '23 | C19: Photomath, Inc. | D19: Google LLC | E19: Acquisition / Merger | F19: - | G19: - | H19: Buyer | I19: Internet Software/Services
A20: 17 Dec '22 | B20: 17 Dec '22 | C20: Korulab, Inc. | D20: Google LLC | E20: Acquisition / Merger | F20: - | G20: - | H20: Buyer | I20: Packaged Software
A21: 14 Dec '22 | B21: 14 Dec '22 | C21: Open Robotics LLC | D21: Intrinsic Innovation LLC | E21: Majority Stake | F21: - | G21: - | H21: Buyer | I21: Information Technology Services
A22: 06 Dec '22 | B22: 06 Dec '22 | C22: Riskhandler Solutions Ltd. | D22: Applied Systems, Inc. | E22: Acquisition / Merger | F22: - | G22: - | H22: Buyer | I22: Packaged Software
A23: 27 Oct '22 | B23: 27 Oct '22 | C23: Omnipresence, Inc. /Facemoji/ | D23: Google LLC | E23: Acquisition / Merger | F23: 100 | G23: - | H23: Buyer | I23: Packaged Software
A24: 26 Oct '22 | B24: 26 Oct '22 | C24: Sound Life Sciences, Inc. | D24: Google LLC | E24: Acquisition / Merger | F24: - | G24: - | H24: Buyer | I24: Packaged Software
A25: 11 Oct '22 | B25: 11 Oct '22 | C25: BrightBytes, Inc. | D25: Google LLC | E25: Acquisition / Merger | F25: - | G25: - | H25: Buyer | I25: Packaged Software
A26: 29 Sep '22 | B26: 29 Sep '22 | C26: Verily Life Sciences LLC | D26: Swiss Re AG | E26: Minority Stake | F26: - | G26: - | H26: Seller | I26: Packaged Software
A27: 20 Sep '22 | B27: 20 Sep '22 | C27: BreezoMeter Ltd. | D27: Google LLC | E27: Acquisition / Merger | F27: 250 | G27: - | H27: Buyer | I27: Information Technology Services
A28: 20 Sep '22 | B28: 20 Sep '22 | C28: Phiar Technologies, Inc. | D28: Google LLC | E28: Acquisition / Merger | F28: - | G28: - | H28: Buyer | I28: Packaged Software
A29: 16 Aug '22 | B29: 16 Aug '22 | C29: Tarmika, Inc. | D29: Applied Systems, Inc. | E29: Acquisition / Merger | F29: - | G29: - | H29: Buyer | I29: Packaged Software
A30: 04 May '22 | B30: 04 May '22 | C30: Raxium, Inc. | D30: Google LLC | E30: Acquisition / Merger | F30: 1000 | G30: 15957.9 | H30: Buyer | I30: Electrical Products
A31: 29 Apr '22 | B31: 29 Apr '22 | C31: MobiledgeX, Inc. | D31: Google Cloud | E31: Acquisition / Merger | F31: - | G31: - | H31: Buyer | I31: Packaged Software
A32: 23 Apr '22 | B32: 23 Apr '22 | C32: Vicarious FPC, Inc. | D32: Intrinsic Innovation LLC | E32: Acquisition / Merger | F32: - | G32: - | H32: Buyer | I32: Packaged Software
A33: 08 Mar '22 | B33: 12 Sep '22 | C33: Mandiant, Inc. | D33: Google LLC | E33: Acquisition / Merger | F33: 4700.5 | G33: -20.7 | H33: Buyer | I33: Information Technology Services
A34: 13 Jan '22 | B34: 13 Jan '22 | C34: Linden Research, Inc. | D34: High Fidelity, Inc. | E34: Majority Stake | F34: - | G34: - | H34: Buyer | I34: Packaged Software
A35: 13 Jan '22 | B35: 13 Jan '22 | C35: Tomorrow Ideas, Inc. | D35: Ethos Technologies, Inc. | E35: Acquisition / Merger | F35: - | G35: - | H35: Buyer | I35: Packaged Software
A36: 04 Jan '22 | B36: 04 Jan '22 | C36: CyArx Technologies Ltd. | D36: Google LLC | E36: Acquisition / Merger | F36: 500 | G36: - | H36: Buyer | I36: Information Technology Services
A37: 17 Nov '21 | B37: 17 Nov '21 | C37: TAP Sound System SAS | D37: Google France SARL | E37: Acquisition / Merger | F37: - | G37: - | H37: Buyer | I37: Packaged Software
A38: 20 Oct '21 | B38: 20 Oct '21 | C38: Compilerworks, Inc. | D38: Google LLC | E38: Acquisition / Merger | F38: - | G38: - | H38: Buyer | I38: Packaged Software
A39: 18 Oct '21 | B39: 18 Oct '21 | C39: MuJoCo | D39: DeepMind Technologies Ltd. | E39: Acquisition / Merger | F39: - | G39: - | H39: Buyer | I39: Miscellaneous Commercial Services
A40: 30 Sep '21 | B40: 30 Sep '21 | C40: Loon LLC /Intellectual Property & Patents/ | D40: Aerostar International LLC | E40: Acquisition / Merger | F40: - | G40: - | H40: Seller | I40: Miscellaneous Commercial Services
A41: 30 Sep '21 | B41: 30 Sep '21 | C41: Boston Polarimetrics, Inc. | D41: Vicarious FPC, Inc. | E41: Acquisition / Merger | F41: - | G41: - | H41: Buyer | I41: Packaged Software
A42: 04 Sep '21 | B42: 04 Sep '21 | C42: Playspace SL | D42: Google LLC | E42: Acquisition / Merger | F42: - | G42: - | H42: Buyer | I42: Packaged Software
A43: 03 Sep '21 | B43: 03 Sep '21 | C43: Aspen Designs, Inc. | D43: Google LLC | E43: Acquisition / Merger | F43: - | G43: - | H43: Buyer | I43: Packaged Software
A44: 10 Aug '21 | B44: 10 Aug '21 | C44: Intrigue Corp. | D44: Mandiant LLC | E44: Acquisition / Merger | F44: - | G44: - | H44: Buyer | I44: Packaged Software
A45: 20 Jul '21 | B45: 20 Jul '21 | C45: SZS Tech Pvt Ltd. | D45: YouTube LLC | E45: Acquisition / Merger | F45: - | G45: - | H45: Buyer | I45: Apparel/Footwear Retail
A46: 13 Jul '21 | B46: 21 Sep '21 | C46: pring, Inc. | D46: Google LLC | E46: Acquisition / Merger | F46: - | G46: - | H46: Buyer | I46: Packaged Software
A47: 14 Jun '21 | B47: 14 Jun '21 | C47: Trustworthy AI, Inc. | D47: Waymo LLC | E47: Acquisition / Merger | F47: - | G47: - | H47: Buyer | I47: Information Technology Services
A48: 07 May '21 | B48: 07 May '21 | C48: Provino Technologies, Inc. | D48: Google LLC | E48: Acquisition / Merger | F48: - | G48: - | H48: Buyer | I48: Packaged Software
... A56: 25 Aug '20 | B56: 25 Aug '20 | C56: StratoZone LLC | D56: Google LLC | E56: Acquisition / Merger | F56: - | G56: - | H56: Buyer | I56: Packaged Software
A57: 17 Aug '20 | B57: Rumor | C57: Mohalla Tech Pvt Ltd. | D57: Google LLC | E57: Acquisition / Merger | F57: 1030 | G57: -11.5 | H57: Buyer | I57: Packaged Software
A58: 30 Jun '20 | B58: 30 Jun '20 | C58: North, Inc. | D58: Google LLC | E58: Acquisition / Merger | F58: 131.4 | G58: - | H58: Buyer | I58: Miscellaneous Commercial Services
A59: 01 Jun '20 | B59: 01 Jun '20 | C59: Western Airways, Inc. | D59: Wing Aviation Charter Services LLC | E59: Acquisition / Merger | F59: - | G59: - | H59: Seller | I59: Airlines
A60: 13 May '20 | B60: 24 Jun '20 | C60: Ten-X, Inc. | D60: CoStar Group, Inc. | E60: Acquisition / Merger | F60: 190 | G60: - | H60: Seller | I60: Real Estate Development
A61: 27 Apr '20 | B61: Rumor Cancelled | C61: D2IQ, Inc. | D61: Google LLC | E61: Acquisition / Merger | F61: 775 | G61: -33.1 | H61: Buyer | I61: Data Processing Services
A62: 19 Feb '20 | B62: 19 Feb '20 | C62: Cornerstone Technology BV | D62: Google LLC | E62: Acquisition / Merger | F62: - | G62: - | H62: Buyer | I62: Information Technology Services
A63: 14 Jan '20 | B63: 14 Jan '20 | C63: Pomo Search Ltd. | D63: Google LLC | E63: Acquisition / Merger | F63: 163 | G63: -18.3 | H63: Buyer | I63: Packaged Software
A64: 14 Jan '20 | B64: 14 Jan '20 | C64: SolveBot, Inc. | D64: Google LLC | E64: Acquisition / Merger | F64: - | G64: - | H64: Buyer | I64: Packaged Software
A65: 06 Jan '20 | B65: 11 Feb '20 | C65: Armis, Inc. | D65: Private Equity Group | E65: Acquisition / Merger | F65: 1100 | G65: -10298.9 | H65: Buyer | I65: Packaged Software
A66: 01 Jan '20 | B66: 01 Jan '20 | C66: Cape Productions, Inc. | D66: Motorola Solutions, Inc. | E66: Acquisition / Merger | F66: - | G66: - | H66: Seller | I66: Movies/Entertainment
A67: 19 Dec '19 | B67: 24 Jan '20 | C67: Shape Security, Inc. | D67: F5 Networks, Inc. | E67: Acquisition / Merger | F67: 1028 | G67: -90 | H67: Seller | I67: Packaged Software
A68: 19 Dec '19 | B68: 19 Dec '19 | C68: Typhoon Studios, Inc. | D68: Google LLC | E68: Acquisition / Merger | F68: - | G68: - | H68: Buyer | I68: Packaged Software
A69: 12 Dec '19 | B69: 12 Dec '19 | C69: Latent Logic Ltd. | D69: Waymo LLC | E69: Acquisition / Merger | F69: - | G69: - | H69: Buyer | I69: Packaged Software
A70: 04 Dec '19 | B70: 04 Dec '19 | C70: Dataiku, Inc. | D70: CapitalG Management Co. LLC | E70: Acquisition / Merger | F70: - | G70: - | H70: Buyer | I70: Packaged Software
A71: 21 Nov '19 | B71: 31 Dec '19 | C71: The Players Tribune, Inc. | D71: Sportority Ltd. | E71: Acquisition / Merger | F71: - | G71: - | H71: Seller | I71: Advertising/Marketing Services
A72: 18 Nov '19 | B72: 21 Nov '19 | C72: Rodin Therapeutics, Inc. | D72: Alkermes, Inc. | E72: Acquisition / Merger | F72: 950 | G72: -1229 | H72: Seller | I72: Biotechnology
A73: 18 Nov '19 | B73: 18 Nov '19 | C73: CloudSimple, Inc. | D73: Google LLC | E73: Acquisition / Merger | F73: - | G73: - | H73: Buyer | I73: Internet Software/Services
A74: 04 Nov '19 | B74: 09 Dec '19 | C74: Scout RFP, Inc. | D74: Workday, Inc. | E74: Acquisition / Merger | F74: 540 | G74: -100.5 | H74: Seller | I74: Packaged Software
A75: 01 Nov '19 | B75: 14 Jan '21 | C75: Fitbit, Inc. | D75: Google LLC | E75: Acquisition / Merger | F75: 1594.4 | G75: -11.8 | H75: Buyer | I75: Electronic Equipment/Instruments
A76: 15 Oct '19 | B76: 15 Oct '19 | C76: Policy Works, Inc. | D76: Applied Systems, Inc. | E76: Acquisition / Merger | F76: - | G76: - | H76: Buyer | I76: Packaged Software
A77: 30 Sep '19 | B77: 30 Sep '19 | C77: Jaunt, Inc. (California) | D77: Verizon Communications, Inc. | E77: Acquisition / Merger | F77: - | G77: - | H77: Seller | I77: Packaged Software
A78: 20 Sep '19 | B78: 09 Oct '19 | C78: Aroundtown SA /2 Subs/ | D78: Google Germany GmbH | E78: Acquisition / Merger | F78: - | G78: - | H78: Buyer | I78: Real Estate Development
A79: 27 Aug '19 | B79: 27 Aug '19 | C79: Apptimize, Inc. | D79: Airship Group, Inc. | E79: Acquisition / Merger | F79: - | G79: - | H79: Seller | I79: Packaged Software
A80: 21 Aug '19 | B80: 21 Aug '19 | C80: Scotty Labs, Inc. | D80: DoorDash, Inc. | E80: Acquisition / Merger | F80: - | G80: - | H80: Seller | I80: Motor Vehicles
A81: 06 Aug '19 | B81: 06 Sep '19 | C81: Rizio, Inc. | D81: Cisco Systems, Inc. | E81: Acquisition / Merger | F81: - | G81: - | H81: Seller | I81: Packaged Software
A82: 05 Aug '19 | B82: 05 Aug '19 | C82: MapR Technologies, Inc. | D82: Hewlett Packard Enterprise Co. | E82: Acquisition / Merger | F82: 50 | G82: -2.5 | H82: Seller | I82: Packaged Software
A83: 03 Aug '19 | B83: 03 Aug '19 | C83: Shopsense Retail Technologies Ltd. | D83: Reliance Industrial Investments & Holdings Ltd. | E83: Majority Stake | F83: 42.4 | G83: -6.2 | H83: Seller | I83: Packaged Software
A84: 15 Jul '19 | B84: 30 Sep '19 | C84: Vungle, Inc. | D84: Blackstone Corporate Private Equity | E84: Acquisition / Merger | F84: 750 | G84: - | H84: Seller | I84: Packaged Software
A85: 09 Jul '19 | B85: 10 Jul '19 | C85: Elastifile, Inc. | D85: Google Cloud India Pvt Ltd. | E85: Acquisition / Merger | F85: 200 | G85: -122.4 | H85: Buyer | I85: Computer Peripherals
A86: 25 Jun '19 | B86: 25 Jun '19 | C86: Mighty AI, Inc. | D86: Uber Technologies, Inc. | E86: Acquisition / Merger | F86: - | G86: - | H86: Seller | I86: Packaged Software
A87: 14 Jun '19 | B87: 14 Jun '19 | C87: ZappRx, Inc. | D87: Allscripts Healthcare Solutions, Inc. | E87: Acquisition / Merger | F87: - | G87: - | H87: Seller | I87: Miscellaneous Commercial Services
A88: 10 Jun '19 | B88: 10 Jul '19 | C88: Barefoot Networks, Inc. | D88: Intel Corp. | E88: Acquisition / Merger | F88: - | G88: - | H88: Seller | I88: Miscellaneous Commercial Services
A89: 06 Jun '19 | B89: 13 Feb '20 | C89: Looker Data Sciences, Inc. | D89: Google LLC | E89: Acquisition / Merger | F89: 2600 | G89: 107.4 | H89: Buyer | I89: Packaged Software
A90: 30 May '19 | B90: 30 May '19 | C90: Recorded Future, Inc. | D90: Insight Venture Management LLC | E90: Acquisition / Merger | F90: 780 | G90: 111.5 | H90: Seller | I90: Investment Managers
A91: 14 May '19 | B91: 14 May '19 | C91: Sisense SF, Inc. | D91: SiSense, Inc. | E91: Acquisition / Merger | F91: 100 | G91: -487.7 | H91: Seller | I91: Medical Specialties
A92: 09 May '19 | B92: 09 May '19 | C92: ContextMedia Health LLC | D92: Littlejohn & Co. LLC | E92: Majority Stake | F92: - | G92: - | H92: Seller | I92: Medical/Nursing Services
A93: 04 Apr '19 | B93: 04 Apr '19 | C93: ClearStory Data, Inc. | D93: Alteryx, Inc. | E93: Acquisition / Merger | F93: 20 | G93: 10.4 | H93: Seller | I93: Data Processing Services
A94: 02 Apr '19 | B94: 02 Apr '19 | C94: Kinema Systems, Inc. | D94: Boston Dynamics, Inc. | E94: Acquisition / Merger | F94: - | G94: - | H94: Buyer | I94: Industrial Machinery
A95: 04 Mar '19 | B95: 01 Apr '19 | C95: Mist Systems, Inc. | D95: Juniper Networks, Inc. | E95: Acquisition / Merger | F95: 359.2 | G95: - | H95: Seller | I95: Information Technology Services
A96: 21 Feb '19 | B96: 21 Feb '19 | C96: Pumpkinhead, Inc. | D96: Broadly, Inc. | E96: Acquisition / Merger | F96: - | G96: - | H96: Seller | I96: Internet Software/Services
A97: 19 Feb '19 | B97: 12 Mar '21 | C97: Alooma, Inc. | D97: Google LLC | E97: Acquisition / Merger | F97: 150 | G97: - | H97: Buyer | I97: Data Processing Services
A98: 06 Feb '19 | B98: 14 Feb '19 | C98: Anchor FM, Inc. | D98: Spotify Technology SA | E98: Acquisition / Merger | F98: 155.2 | G98: - | H98: Seller | I98: Packaged Software
A99: 28 Jan '19 | B99: 08 Feb '19 | C99: JN Projects, Inc. | D99: Dropbox, Inc. | E99: Acquisition / Merger | F99: 226.4 | G99: - | H99: Seller | I99: Miscellaneous Commercial Services
A100: 17 Jan '19 | B100: Pending | C100: Fossil Group, Inc. /Smartwatch Asset/ | D100: Google LLC | E100: Acquisition / Merger | F100: 40 | G100: - | H100: Buyer | I100: Apparel/Footwear
A101: 03 Jan '19 | B101: 03 Jan '19 | C101: Superpod.io | D101: Google LLC | E101: Acquisition / Merger | F101: 60 | G101: - | H101: Buyer | I101: Internet Software/Services
A102: 13 Dec '18 | B102: 13 Dec '18 | C102: VigLink, Inc. | D102: Sovrn Holdings, Inc. | E102: Acquisition / Merger | F102: - | G102: - | H102: Seller | I102: Information Technology Services
A103: 12 Dec '18 | B103: 12 Dec '18 | C103: Walker & Company Brands, Inc. | D103: Procter & Gamble Co. | E103: Acquisition / Merger | F103: 40 | G103: -68.4 | H103: Seller | I103: Other Consumer Services
A104: 10 Dec '18 | B104: 10 Dec '18 | C104: Sigmoid Labs Pvt Ltd. | D104: Google LLC | E104: Acquisition / Merger | F104: 0.6 | G104: - | H104: Buyer | I104: Information Technology Services
A105: 27 Nov '18 | B105: 27 Nov '18 | C105: cwist, Inc. | D105: Google LLC | E105: Acquisition / Merger | F105: - | G105: - | H105: Buyer | I105: Miscellaneous Commercial Services
A106: 19 Nov '18 | B106: 19 Nov '18 | C106: Solar Service Experts LLC | D106: Highbridge Principal Strategies Growth Equity | E106: Acquisition / Merger | F106: - | G106: - | H106: Seller | I106: Alternative Power Generation
A107: 09 Nov '18 | B107: 09 Nov '18 | C107: Amimon, Inc. | D107: The Vitec Group Plc | E107: Acquisition / Merger | F107: 55 | G107: 10.6 | H107: Seller | I107: Semiconductors
A108: 05 Nov '18 | B108: 05 Nov '18 | C108: Reserve Media, Inc. | D108: Resy Network, Inc. | E108: Acquisition / Merger | F108: - | G108: - | H108: Seller | I108: Information Technology Services
...

Sheet Annual reports
S6: 2009 | T6: 108204000
S7: 2008 | T7: 3320299000
S8: 2007 | T8: 906651000
S9: 2006 | T9: 402446000
S10: 2005 | T10: 101310000
S11: 2004 | T11: 58863000
N25: https://materials.proxyvote.com/Approved/38259P/20100315/AR_56325/HTML2/google-ar2009_0082.htm
N26: 2009
A28: https://abc.xyz/assets/77/51/9841ad5c4fbe85b4440c47a4df8d/goog-10-k-2024.pdf | G28: https://abc.xyz/assets/43/44/675b83d7455885c4615d848d52a4/goog-10-k-2023.pdf | L28: GOOG 10-K 2023
A29: GOOG 10-K 2024
A31: https://abc.xyz/assets/d4/4f/a48b94d548d0b2fdc029a95e8c63/2022-alphabet-annual-report.pdf | G31: 2022-alphabet-annual-report.pdf
U32: https://abc.xyz/assets/investor/static/pdf/2007_google_annual_report.pdf | Z32: 2007
A33: https://abc.xyz/assets/investor/static/pdf/2021_alphabet_annual_report.pdf | G33: GOOG019_Alphabet_2021-Annual-Report_Web.pdf
A35: https://abc.xyz/assets/51/9a/52377a1f4b268cab701bbde10ce9/2020-alphabet-annual-report.pdf | G35: Rev2_210419_YIR_Cover.indd | R35: https://www.sec.gov/Archives/edgar/data/1288776/000119312506056598/d10k.htm#fin75474_5
R36: 2005
A37: https://abc.xyz/assets/investor/static/pdf/2019_alphabet_annual_report.pdf | G37: 2019
A39: https://abc.xyz/assets/investor/static/pdf/20180204_alphabet_10K.pdf | G39: 2018
A41: https://abc.xyz/assets/investor/static/pdf/20171231_alphabet_10K.pdf | G41: 2017
A43: https://abc.xyz/assets/investor/static/pdf/2016_google_annual_report.pdf | G43: 2016
A45: https://abc.xyz/assets/investor/static/pdf/2015_alphabet_annual_report.pdf | G45: 2015
A47: https://abc.xyz/assets/investor/static/pdf/2014_google_annual_report.pdf | G47: 2014
A49: https://abc.xyz/assets/investor/static/pdf/20131231_google_10K.pdf | G49: 2013
A51: https://abc.xyz/assets/investor/static/pdf/20101231_google_10K.pdf | G51: 2010
